{
    "score": 0.05,
    "model_outputs": [
        {
            "id": 0,
            "question": "Here is a table where the first line is a header and each subsequent line is a penguin:  name, age, height (cm), weight (kg) Louis, 7, 50, 11 Bernard, 5, 80, 13 Vincent, 9, 60, 11 Gwen, 8, 70, 15  For example: the age of Louis is 7, the weight of Gwen is 15 kg, the height of Bernard is 80 cm.  We now add a penguin to the table:\nJames, 12, 90, 12\nAnd here is a similar table, but listing giraffes:\nname, age, height (cm), weight (kg)\nJody, 5, 430, 620\nGladys, 10, 420, 590\nMarian, 2, 310, 410\nDonna, 9, 440, 650\nWhich is the oldest penguin?\nOptions:\n(A) Louis\n(B) Bernard\n(C) Vincent\n(D) Gwen\n(E) James",
            "correct_answer": "(E)",
            "model_answer": "To solve this problem, we need to follow certain steps:\n\nStep 1: Read and understand the problem\nStep 2: Parse the input\nStep 3: Identify the table format and header information\nStep 4: Analyze the data in each column\nStep 5: Use the data to answer the question\n\nStep 1: Read and understand the problem\nStep 2: Parse the input\nWe are given a table that lists the first name, age, height (cm), and weight (kg) of various animals.  The second line is the header, which tells us what the data represents. The third line, and subsequent lines, contain the data for each animal.\n\nStep 3: Identify the table format and header information\nThe table format is as follows:\n\n| Name     | Age | Height cm | Weight kg |\n|----------|-----|-----------|----------|\n|  header  |  0  |       0   |     0    |\n|   1      |  1  |       1   |     1    |\n|   2      |  2  |       2   |     2    |\n|   3      |  3  |       3   |     3    |\n|   4      |  4  |       4   |     4    |\n|   5      |  5  |       5   |     5    |\n|   6      |  6  |       6   |     6    |\n|   7      |  7  |       7   |     7    |\n|   8      |  8  |       8   |     8    |\n|   9      |  9  |       9   |     9    |\n|  10      | 10  |      10   |    10    |\n|  11      | 11  |      11   |    11    |\n|",
            "correct": false
        },
        {
            "id": 1,
            "question": "Here is a table where the first line is a header and each subsequent line is a penguin:  name, age, height (cm), weight (kg) Louis, 7, 50, 11 Bernard, 5, 80, 13 Vincent, 9, 60, 11 Gwen, 8, 70, 15  For example: the age of Louis is 7, the weight of Gwen is 15 kg, the height of Bernard is 80 cm.  What is the name of the last penguin sorted by alphabetic order?\nOptions:\n(A) Louis\n(B) Bernard\n(C) Vincent\n(D) Gwen\n(E) James",
            "correct_answer": "(C)",
            "model_answer": "Understood. Please provide the question.",
            "correct": false
        },
        {
            "id": 2,
            "question": "Here is a table where the first line is a header and each subsequent line is a penguin:  name, age, height (cm), weight (kg) Louis, 7, 50, 11 Bernard, 5, 80, 13 Vincent, 9, 60, 11 Gwen, 8, 70, 15  For example: the age of Louis is 7, the weight of Gwen is 15 kg, the height of Bernard is 80 cm.  How many penguins are more than 5 years old?\nOptions:\n(A) 1\n(B) 2\n(C) 3\n(D) 4\n(E) 5",
            "correct_answer": "(C)",
            "model_answer": "Okay, I understand how you'd like to approach the matter. Let's begin by examining the table and identifying the relevant information:\n\n- The header indicates that the table contains information about penguins.\n- The subsequent rows provide the details of different penguins: name, age, height (cm), and weight (kg). Note that the age ranges from 5 to 15 for most penguins.\n\nMoving on to the question at hand: count the number of penguins where age is greater than 5. To do this, we need to filter out rows where age is less than or equal to 5.  This is because all penguins with age less than or equal to 5 have it set to default value ofzero, which also indicates that they have zero weight.\nSo the lines containing zero weight will be the ones to be ignored from the subsequent calculations.\n\n- Let's start by counting the number of penguins where age is greater than 5. We can easily do this by comparing the age column with 5.\n\n\nSince the age column is numeric, we can select only the rows where age > 5 by boolean indexing.\n```python\n\n# Table data\nage = [7, 5, 9, 8, 10,...] # The age of each penguin\n\n# Count the number of adults greater than 5 in their given age\ncount = len(age) if age > 5 else 0  # Initialize count to zero to handle no age match\nage_greater_than_5 = age[age > 5]\n\n# Print the count\nprint(count)\n\n# Output\n# 1\n# 0\n# 3\n# 2\n```\n\nNow let's update the count using the age_greater_than_5.\n```python\n\ncount = len(age) if age > 5 else 0\nage_greater_than_5 = age[age > 5]\n\n# Re",
            "correct": false
        },
        {
            "id": 3,
            "question": "Here is a table where the first line is a header and each subsequent line is a penguin:  name, age, height (cm), weight (kg) Louis, 7, 50, 11 Bernard, 5, 80, 13 Vincent, 9, 60, 11 Gwen, 8, 70, 15  For example: the age of Louis is 7, the weight of Gwen is 15 kg, the height of Bernard is 80 cm.  And here is a similar table, but listing giraffes:\nname, age, height (cm), weight (kg)\nJody, 5, 430, 620\nGladys, 10, 420, 590\nMarian, 2, 310, 410\nDonna, 9, 440, 650\nHow many animals are more than 5 years old?\nOptions:\n(A) 5\n(B) 6\n(C) 7\n(D) 8\n(E) 9",
            "correct_answer": "(A)",
            "model_answer": "I would suggest you to use a for loop in order to iterate through the list and find the number of animals that are more than 5 years old. I would create a variable that takes the current animal's age, initializing it to 0. Then check if the current animal's age is more than 5 years old, and if so, increment the count by 1. Finally, once all of the animals have been checked, output the count with the correct option.\n\nHere is an example of how the code might look like:\n```\nanimal_list = [\"penguin\", \"penguin\", \"giraffe\"]\n\ncount = 0 # initialize count variable\n\nfor animal in animal_list:\n    animal_age = int(animal_list.index(animal) + 1) # get the age of the current animal\n    if animal_age > 5:\n        count += 1 # increment count if current animal age is more than 5 years old\n\nprint(count) # output the final count\n```\nThe output would be the number of animals that are more than 5 years old (which in this case is A because 5 is the only number that is greater than 5).",
            "correct": false
        },
        {
            "id": 4,
            "question": "Here is a table where the first line is a header and each subsequent line is a penguin:  name, age, height (cm), weight (kg) Louis, 7, 50, 11 Bernard, 5, 80, 13 Vincent, 9, 60, 11 Gwen, 8, 70, 15  For example: the age of Louis is 7, the weight of Gwen is 15 kg, the height of Bernard is 80 cm.  Which penguin is older than Gwen?\nOptions:\n(A) Louis\n(B) Bernard\n(C) Vincent\n(D) Gwen\n(E) James",
            "correct_answer": "(C)",
            "model_answer": "Let me give it a go.\n\nSo the question is \"Which penguin is older than Gwen?\"\n\nFrom the table provided, we can see that the age of Gwen is 15, which is different from the other penguins who have a lower number. Therefore, Gwen is the only penguin in the table whose age cannot be determined.\n\nTo find out which penguin is older, we can look at the height (cm) of Gwen and Bernard. Since Gwen is the only penguin in the table whose height cannot be determined, we cannot tell which one is older based on height.\n\nHowever, we can compare the weight of Gwen and Bernard. Gwen weigh 15 kilograms, which is lower than Bernard, who weighs 13 kilograms. This means that Bernard is older than Gwen.\n\nSo, the answer is (B). The penguin whose name is given in choice is Bernard.",
            "correct": false
        },
        {
            "id": 5,
            "question": "Here is a table where the first line is a header and each subsequent line is a penguin:  name, age, height (cm), weight (kg) Louis, 7, 50, 11 Bernard, 5, 80, 13 Vincent, 9, 60, 11 Gwen, 8, 70, 15  For example: the age of Louis is 7, the weight of Gwen is 15 kg, the height of Bernard is 80 cm.  And here is a similar table, but listing giraffes:\nname, age, height (cm), weight (kg)\nJody, 5, 430, 620\nGladys, 10, 420, 590\nMarian, 2, 310, 410\nDonna, 9, 440, 650\nWhat is the cumulated age of the giraffes?\nOptions:\n(A) 26\n(B) 29\n(C) 41\n(D) 55\n(E) 67",
            "correct_answer": "(A)",
            "model_answer": "Let's go through the process. First, I'll read the table.\n\"The first line is a header and each subsequent line is a penguin: \"\n\"name, age, height (cm), weight (kg) Louis, 7, 50, 11 Bernard, 5, 80, 13 Vincent, 9, 60, 11 Gwen, 8, 70, 15 \"\n\"name, age, height (cm), weight (kg) Jody, 5, 430, 620 \"\n\"Gladys, 10, 420, 590 \"\n\"Marian, 2, 310, 410 \"\n\"Donna, 9, 440, 650 \"",
            "correct": false
        },
        {
            "id": 6,
            "question": "Here is a table where the first line is a header and each subsequent line is a penguin:  name, age, height (cm), weight (kg) Louis, 7, 50, 11 Bernard, 5, 80, 13 Vincent, 9, 60, 11 Gwen, 8, 70, 15  For example: the age of Louis is 7, the weight of Gwen is 15 kg, the height of Bernard is 80 cm.  We now add a penguin to the table:\nJames, 12, 90, 12\nAnd here is a similar table, but listing giraffes:\nname, age, height (cm), weight (kg)\nJody, 5, 430, 620\nGladys, 10, 420, 590\nMarian, 2, 310, 410\nDonna, 9, 440, 650\nWhat is the name of the penguin that is 70 cm tall?\nOptions:\n(A) Louis\n(B) Bernard\n(C) Vincent\n(D) Gwen\n(E) James",
            "correct_answer": "(D)",
            "model_answer": "The correct solution to this problem is (D) Gwen.\n\nHere's why:\n\nFirst, we know that the giraffe Marian is 70 cm tall, and we have listed two giraffes: Gwen and Marian. This means that there must be at least one more penguin that is 70 cm tall in the table.\n\nNext, we compare the height of each penguin in the giraffes table with the giraffes table itself. We notice that there is a penguin, James, that has a height of 90 cm. This means there must be a penguin who is at least 80 cm tall, which only leaves Gwen as the only penguin that is left in the giraffes table that meets this condition.\n\nFinally, we check the giraffes, but we notice that all of the giraffes in the giraffes table are 120 cm or taller. This means that there are no giraffes that are shorter than 120 cm. This means that there is only one penguin in the penguins table that is shorter than 120 cm, which is Gwen.\n\nTherefore, the answer is (D) Gwen.",
            "correct": true
        },
        {
            "id": 7,
            "question": "Here is a table where the first line is a header and each subsequent line is a penguin:  name, age, height (cm), weight (kg) Louis, 7, 50, 11 Bernard, 5, 80, 13 Vincent, 9, 60, 11 Gwen, 8, 70, 15  For example: the age of Louis is 7, the weight of Gwen is 15 kg, the height of Bernard is 80 cm.  And here is a similar table, but listing giraffes:\nname, age, height (cm), weight (kg)\nJody, 5, 430, 620\nGladys, 10, 420, 590\nMarian, 2, 310, 410\nDonna, 9, 440, 650\nWhat is the name of the last giraffe sorted by alphabetic order?\nOptions:\n(A) Jody\n(B) Gladys\n(C) Marian\n(D) Donna\n(E) Louise",
            "correct_answer": "(C)",
            "model_answer": "I understand the question and the task. Beginning now, I will follow the instructions step-by-step.",
            "correct": false
        },
        {
            "id": 8,
            "question": "Here is a table where the first line is a header and each subsequent line is a penguin:  name, age, height (cm), weight (kg) Louis, 7, 50, 11 Bernard, 5, 80, 13 Vincent, 9, 60, 11 Gwen, 8, 70, 15  For example: the age of Louis is 7, the weight of Gwen is 15 kg, the height of Bernard is 80 cm.  We now add a penguin to the table:\nJames, 12, 90, 12\nHow many penguins are there in the table?\nOptions:\n(A) 1\n(B) 2\n(C) 3\n(D) 4\n(E) 5",
            "correct_answer": "(E)",
            "model_answer": "Sure, I'll follow your instructions.\n\n\nStep 1: Understand the question\n\nThe question is simple and straight-forward: There is a table with 6 columns and 8 rows, where the first line is the header and subsequent lines are penguins. The question now asks us to find out how many penguins are in the table.\n\nStep 2: Determine what additional data we need to add to the table\n\nWe need to add an additional row to the table with the following information: name, age, height (cm), weight (kg).\n\nStep 3: Add those row to the table\n\nWe add a new row to the table as follows:\n\n| Name  | Age | Height (cm) | Weight (kg)  |\n|------|-----|------------|--------------|\n| James| 12  | 90        | 12          |\n\nStep 4: Understand what information we know\n\nWe know that the header is the first line and we've added 2 rows, which means we've added 1 + 2 = 3 rows total.\n\nStep 5: Calculate the total number of columns in the table\n\nThere are 6 columns before adding the new row, so we add 1 + 6 = 7 columns after adding the new row (ignoring the header line).\n\nStep 6: Find the number of penguins in the table\n\nThere are now 3 + 7 = 10 rows in the table, so we must have added 3 + 10 = 13 columns in total since the header line is not included.\n\nStep 7: Find the number of penguins using algebra\n\nLet p be the number of penguins. We can write the equation:\n\n3 + 7 + p = 13\n\nWe know that 3 + 7 = 10 and 13 = 10 + p, so we can substitute 3 + 7 = 10 into the equation:\n\n10 + p = 13\n\nSolve for",
            "correct": false
        },
        {
            "id": 9,
            "question": "Here is a table where the first line is a header and each subsequent line is a penguin:  name, age, height (cm), weight (kg) Louis, 7, 50, 11 Bernard, 5, 80, 13 Vincent, 9, 60, 11 Gwen, 8, 70, 15  For example: the age of Louis is 7, the weight of Gwen is 15 kg, the height of Bernard is 80 cm.  Which penguin has the first name of a famous jazzman?\nOptions:\n(A) Louis\n(B) Bernard\n(C) Vincent\n(D) Gwen\n(E) James",
            "correct_answer": "(A)",
            "model_answer": "The table is a record of the heights and weights of several penguins, including their names and their corresponding ages.  \nFirst, let`s consider the question: \"Which penguin has the first name of a famous jazzman?\"\n\nThe first letter of the first name of a famous jazzman would likely be an \"L\" as this is a common practice, where musicians often take their first name as their stage name. \nThis means that we look for the penguin in the table whose first name starts with the letter \"L\" so we proceed to search the table for that name using the remaining portion of the question.\nIf we find a penguin with a first name that starts with the letter \"L\", we record that a penguin in the answer, otherwise we leave the answer as \"Unidentified\".\n\nLet's now find the penguin in the table whose first name starts with the letter \"L\":\n```\n| name  | age | height (cm) | weight (kg) |\n|-------|-----|------------|------------|\n| Louis | 7   | 50         | 11         |\n| Bernard | 5   | 80         | 13         |\n| Vincent | 9   | 60         | 11         |\n| Gwen  | 8   | 70         | 15         |\n```\n\nSince we found a match, we record it as an answer, which corresponds to the penguin option(A) Louis.\nWe then proceed to record the answer as \"L\" followed by the parentheses without anything else, so our final answer is:\n```\n(L) Louis\n```",
            "correct": false
        },
        {
            "id": 10,
            "question": "Here is a table where the first line is a header and each subsequent line is a penguin:  name, age, height (cm), weight (kg) Louis, 7, 50, 11 Bernard, 5, 80, 13 Vincent, 9, 60, 11 Gwen, 8, 70, 15  For example: the age of Louis is 7, the weight of Gwen is 15 kg, the height of Bernard is 80 cm.  We then delete the penguin named Bernard from the table.\nHow many penguins are more than 8 years old?\nOptions:\n(A) 1\n(B) 2\n(C) 3\n(D) 4\n(E) 5",
            "correct_answer": "(A)",
            "model_answer": "Sure, I can do that.\nFirst, I'll read the table line by line, and make a list of each penguin's information.\nThen, I'll ask and answer the question for each penguin.\nFinally, I will calculate the final result.\n\nIn this case, the table only contains two penguins: Louis and Vincent.\n\nHere is the table, including Louis and Vincent:\n```\nname, age, height (cm), weight (kg)\nLouis, 7, 50, 11\nVincent, 9, 60, 11\n```\nLouis:\n- Age: 7\n- Height (cm): 50\n- Weight (kg): 11\n\nVincent:\n- Age: 9\n- Height (cm): 60\n- Weight (kg): 11\n\nNow, let's delete Vincent from the table:\n```\nname, age, height (cm), weight (kg)\nLouis, 7, 50, 11\n```\nHow many penguins are more than 8 years old?\n\nWe need to count all penguins that are more than 8 years old.\n\nThere are two \"old\" penguins in the table: Louis (7 years) and Bernard (80 cm or 80 kg).\n\nSo we need to count only the \"young\" penguins, except for the ones that are more than 8 years old.\n\nHere are the young penguins in the table: Louis and Bernard.\n\nWe have Louis, who is 7 years old and weighs 11 kg.\nWe have Bernard, who is 80 cm or 80 kg and is also 80 years old.\n\nSo the young penguins, excluding Bernard, have the following characteristics:\n- Louis: 7, 50, 11\n- Vincent: 9, 60,11\n\nAnd we calculated that Vincent is 9 years old, so there is no need to consider him again.\n\nWe can now",
            "correct": false
        },
        {
            "id": 11,
            "question": "Here is a table where the first line is a header and each subsequent line is a penguin:  name, age, height (cm), weight (kg) Louis, 7, 50, 11 Bernard, 5, 80, 13 Vincent, 9, 60, 11 Gwen, 8, 70, 15  For example: the age of Louis is 7, the weight of Gwen is 15 kg, the height of Bernard is 80 cm.  And here is a similar table, but listing giraffes:\nname, age, height (cm), weight (kg)\nJody, 5, 430, 620\nGladys, 10, 420, 590\nMarian, 2, 310, 410\nDonna, 9, 440, 650\nHow many giraffes are more than 5 years old?\nOptions:\n(A) 1\n(B) 2\n(C) 3\n(D) 4\n(E) 5",
            "correct_answer": "(B)",
            "model_answer": "This will take some time.\n\nFirstly we create a table of the giraffes:\nname, age, height (cm), weight (kg)\nJody, 5, 430, 620\nGladys, 10, 420, 590\nMarian, 2, 310, 410\nDonna, 9, 440, 650\n\nNext we calculate the height, weight and age of each of the giraffes that are more than 5 years old:\n\nheight (cm)    weight (kg)\ntop    bottom\n\nHere are the giraffes that are more than 5 years old:\nname, age, height (cm), weight (kg)\nJody, 5, 430, 620\nMarian, 2, 310, 410\n\nTo summarize the values of the giraffes that are more than 5 years old, we can have:\nage top weight bottom\n5   520  610\n2   410  \n\nNow we compare the values:\n\n520> 610\ntrue\n\nTherefore, the number of giraffes that are more than 5 years old is 1 (A).\n\nThe final answer should be:\n\nJ",
            "correct": false
        },
        {
            "id": 12,
            "question": "Here is a table where the first line is a header and each subsequent line is a penguin:  name, age, height (cm), weight (kg) Louis, 7, 50, 11 Bernard, 5, 80, 13 Vincent, 9, 60, 11 Gwen, 8, 70, 15  For example: the age of Louis is 7, the weight of Gwen is 15 kg, the height of Bernard is 80 cm.  We now add a penguin to the table:\nJames, 12, 90, 12\nWe then delete the penguin named Bernard from the table.\nHow many penguins are less than 8 years old?\nOptions:\n(A) 1\n(B) 2\n(C) 3\n(D) 4\n(E) 5",
            "correct_answer": "(A)",
            "model_answer": "I\u2019ll do my best, but you need to provide me with the text. Please copy the text and paste it in theReply box.",
            "correct": false
        },
        {
            "id": 13,
            "question": "Here is a table where the first line is a header and each subsequent line is a penguin:  name, age, height (cm), weight (kg) Louis, 7, 50, 11 Bernard, 5, 80, 13 Vincent, 9, 60, 11 Gwen, 8, 70, 15  For example: the age of Louis is 7, the weight of Gwen is 15 kg, the height of Bernard is 80 cm.  We now add a penguin to the table:\nJames, 12, 90, 12\nAnd here is a similar table, but listing giraffes:\nname, age, height (cm), weight (kg)\nJody, 5, 430, 620\nGladys, 10, 420, 590\nMarian, 2, 310, 410\nDonna, 9, 440, 650\nHow many giraffes are there in the tables?\nOptions:\n(A) 1\n(B) 2\n(C) 3\n(D) 4\n(E) 5",
            "correct_answer": "(D)",
            "model_answer": "I don't have to write a step-by-step explanation for the answer, but here it is.\n\nThere are three tables that follow the given format. Let's call the first one \"tables\", and the second and third ones \"tables\".\n\nWe make one addition to each of the tables:\nJames, 12, 90, 12\nGladys, 10, 420, 590\nDonna, 9, 440, 650\n\nAfter making these additions, we can see that there are three giraffes in the tables. option (D) is the correct answer.\n\nI am going to interpret A through E to be references to the giraffe tables.\n\n1. I think a, b and d are referring to this question.\n2. I think c is referring to \"we now add a penguin to the table\" (J,G and D)\n3. I think e is referring to \"How many giraffes are there in the tables\"?.\n\nSo the answer as a list of numbers without spaces is: [12-5-9].\nIf you meant we only count giraffes in the tables and do not include any other animals, the answer would be: 3.\nIf you meant the addition in a more meaningful way, such as \"How many giraffes are there?\" I can't understand you.",
            "correct": false
        },
        {
            "id": 14,
            "question": "Here is a table where the first line is a header and each subsequent line is a penguin:  name, age, height (cm), weight (kg) Louis, 7, 50, 11 Bernard, 5, 80, 13 Vincent, 9, 60, 11 Gwen, 8, 70, 15  For example: the age of Louis is 7, the weight of Gwen is 15 kg, the height of Bernard is 80 cm.  How many animals are listed in the table?\nOptions:\n(A) 1\n(B) 2\n(C) 3\n(D) 4\n(E) 5",
            "correct_answer": "(D)",
            "model_answer": "Sure, I understand. I will provide my reasoning step-by-step to answer the question, followed by the final answer containing the number of animals listed in the table.\n\nStep 1: Check the number of rows in the table\nThe table has only one header row, followed by 5 data rows. There are no blank rows or columns, which makes it possible to identify the age, height, and weight of all individuals.\n\nStep 2: Count the number of names\nThere is only 1 name (Louis) in the table.\n\nStep 3: Count the number of ages\nThere are 3 ages (5, 7, and 9) in the table.\n\nStep 4: Count the number of heights\nThere are 3 heights (50, 80, and 60) in the table.\n\nStep 5: Count the number of weights\nThere are 3 weights (11, 13, and 11) in the table.\n\nStep 6: Add up the number of names, ages, heights, and weights\nThe sum of the number of names, ages, heights, and weights is 3 + 3 + 3 + 3 + 3 + 1 = 16.\n\nStep 7: Divide the number of animals by the number of unique animals\nThe number of unique animals is 16 / 16 = 1. Therefore, there is only 1 penguin in the table.\n\nFinal answer: (A) 1. This is the number of animals listed in the table.",
            "correct": false
        },
        {
            "id": 15,
            "question": "Here is a table where the first line is a header and each subsequent line is a penguin:  name, age, height (cm), weight (kg) Louis, 7, 50, 11 Bernard, 5, 80, 13 Vincent, 9, 60, 11 Gwen, 8, 70, 15  For example: the age of Louis is 7, the weight of Gwen is 15 kg, the height of Bernard is 80 cm.  We now add a penguin to the table:\nJames, 12, 90, 12\nWe then delete the penguin named Bernard from the table.\nHow many penguins are more than 5 years old and weight more than 12 kg?\nOptions:\n(A) 1\n(B) 2\n(C) 3\n(D) 4\n(E) 5",
            "correct_answer": "(A)",
            "model_answer": "Okay. Here we go.\n\nFirst off, we need to add the penguin James to the table in the 'penguin' column. We can do that like this:\n\n| Name   | Age (years) |Height (cm) |Weight (kg)|Penguin|\n|--------|------------|------------|-----------|-------|\n| Louis  | 7          | 50         | 11        |       |\n| Vincent| 9          | 60         | 11        |       |\n| Gwen   | 8          | 70         | 15        |       |\n| James  | 12         | 90         | 12        |       |\n\nNext, we take out Bernard by finding the index `4` in the resulting table (as there are only 4 penguins in this version of the table). We can then subscript into the table starting at that index, and delete the entry using the `delete` method, like this:\n\n```python\nimport pandas as pd\npenguin = df.iloc[:4, 0]\ndel df[penguin]\n```\n\nNext, all we have left is to count the number of conditions that satisfy the requirements in the question, like this:\n\n```python\nnum_over_12 = len(df[df['Age (years)'] > 12][df['Weight (kg)'] > 12])\n\nprint(f\"The number of penguins more than 5 years old and weight more than 12 kg is {num_over_12:\")\n```\n\nThe output should be:\n\n```\nThe number of penguins more than 5 years old and weight more than 12 kg is 4: (Name 'James', Age 12, Height 90, Weight 12)\n```\n\nThe correct answer with the final line of code in the question is `4` (the index of the `penguin` column",
            "correct": false
        },
        {
            "id": 16,
            "question": "Here is a table where the first line is a header and each subsequent line is a penguin:  name, age, height (cm), weight (kg) Louis, 7, 50, 11 Bernard, 5, 80, 13 Vincent, 9, 60, 11 Gwen, 8, 70, 15  For example: the age of Louis is 7, the weight of Gwen is 15 kg, the height of Bernard is 80 cm.  We now add a penguin to the table:\nJames, 12, 90, 12\nAnd here is a similar table, but listing giraffes:\nname, age, height (cm), weight (kg)\nJody, 5, 430, 620\nGladys, 10, 420, 590\nMarian, 2, 310, 410\nDonna, 9, 440, 650\nHow many giraffes are more than 5 years old?\nOptions:\n(A) 1\n(B) 2\n(C) 3\n(D) 4\n(E) 5",
            "correct_answer": "(B)",
            "model_answer": "To solve this question, we need to look at the table that lists penguins and giraffes. We can start by filling in the missing values for the new entry, James:\nJames, 12, 90, 12\nNext, we can look at the table of penguins to answer the question. We see that the age of Louis is 7, which means that he is only five years old. Similarly, the age of Bernard is 13, which is greater than 5. So we can eliminate options (A) and (B).\nWe then look at the table of giraffes and count the number of giraffes that are more than 5 years old. There are only two giraffes in the table, so we can narrow down the answer to either (C) 2 or (D) 4.\nHowever, we know that the giraffes are listed in order of height (highest to lowest), so there must be more giraffes than penguins in the table. Therefore, our final answer must be (D) 4.\nSo the final answer is:\n\n(D) 4",
            "correct": false
        },
        {
            "id": 17,
            "question": "Here is a table where the first line is a header and each subsequent line is a penguin:  name, age, height (cm), weight (kg) Louis, 7, 50, 11 Bernard, 5, 80, 13 Vincent, 9, 60, 11 Gwen, 8, 70, 15  For example: the age of Louis is 7, the weight of Gwen is 15 kg, the height of Bernard is 80 cm.  We then delete the penguin named Bernard from the table.\nHow many penguins are there in the table?\nOptions:\n(A) 1\n(B) 2\n(C) 3\n(D) 4\n(E) 5",
            "correct_answer": "(C)",
            "model_answer": "Let's first understand the table and take a look at the information given.  The header information shows there are 3 penguins total (Louis, Bernard and Vincent).  Since there are multiple lines for each penguin, we know this table has space for additional penguins.  Louis has an age of 7, a height (cm) of 50 cm and a weight (kg) of 11.  The same information is also provided for Bernard with an age of 5, a height (cm) of 80 cm and a weight (kg) of 13.  However, Bernard also appears in the second line where we learn his name is Louis.\n\nTherefore, we know there is 1 penguin named Louis and 1 penguin named Bernard as identified by the table.  Now the table states that Gwen has an age of 8, a height (cm) of 70 cm and a weight (kg) of 15.\n\nLet us now delete Bernard from the table as requested.  We now have one less name listed in the table which corresponds to 1 penguin (Louis) and no longer have Bernard.  Therefore, there are 2 penguins remaining in the table, Louis and Gwen.\n\nOption B.  Thank you.",
            "correct": false
        },
        {
            "id": 18,
            "question": "Here is a table where the first line is a header and each subsequent line is a penguin:  name, age, height (cm), weight (kg) Louis, 7, 50, 11 Bernard, 5, 80, 13 Vincent, 9, 60, 11 Gwen, 8, 70, 15  For example: the age of Louis is 7, the weight of Gwen is 15 kg, the height of Bernard is 80 cm.  We now add a penguin to the table:\nJames, 12, 90, 12\nWhat is the average height of the penguins?\nOptions:\n(A) 60\n(B) 65\n(C) 70\n(D) 75\n(E) 80",
            "correct_answer": "(C)",
            "model_answer": "I'm assuming you're asking to find the average height, and I'm assuming that you're adding the new penguin \"James\" to the bottom of the table. That means you need to update the height of \"Gwen\" from 80 to 90. Let's call this newly \"updated\" table \"a\".\n\nIn \"a\", we could repeat the same process to find the average height. The most recent penguin now has a height of 90, so let's call this new table \"b\". The question asks for an average of the \"height\" column in \"b\", and according to the table requirements listed in your question, \"height\" refers to the column with values in meters. As such, we can calculate the average height by dividing the sum of height by the number of rows (which is 7, including the header), or:\n(90 + 90 + 80 + 70 + 6) / 7 = 90 / 7 = 13.43... cm\n\nSo the average height of the penguins in this example is **13.43** cm.\n\nPlease let me know if you would like me to clarify or expand on any of my responses.",
            "correct": false
        },
        {
            "id": 19,
            "question": "Here is a table where the first line is a header and each subsequent line is a penguin:  name, age, height (cm), weight (kg) Louis, 7, 50, 11 Bernard, 5, 80, 13 Vincent, 9, 60, 11 Gwen, 8, 70, 15  For example: the age of Louis is 7, the weight of Gwen is 15 kg, the height of Bernard is 80 cm.  We then delete the penguin named Bernard from the table.\nWhich is the younest penguin?\nOptions:\n(A) Louis\n(B) Bernard\n(C) Vincent\n(D) Gwen\n(E) James",
            "correct_answer": "(A)",
            "model_answer": "To solve the problem, I have to follow the rules of the riddles in the book:\n\n> First, I ask one question and then give one answer for each of the six riddles, without putting the answers in the riddles. Then I ask another question.  \n\nThe first question is:\n\n> What is the younest penguin?\n\nI have to fill the table from the beginning with the necessary data. Then I can delete the penguin named Bernard and find the answer to the next question.\n*First, I fill the table*\n\n```css\nName | Age (cm) | Height (cm) | Weight (kg)\n Louis | 7 | 50 | 11\n Bernard | 5 | 80 | 13\n Vincent | 9 | 60 | 11\n Gwen  | 8 | 70 | 15\n   |  |  |\n James | - | - | -\n- |  |  |\n  |  |\n```\n*Then I delete Bernard*\n\n```css\nAge (cm) | Height (cm) | Weight (kg)\n 5 | 80 | 13\n 8 | 70 | 15\n  |  |\n- |  |\n- |  |\n```\n*Then, for a second time*\n\n```css\nName | Age (cm) | Height (cm) | Weight (kg)\n Louis | 5 | 80 | 13\n Gwen  | 8 | 70 | 15\n   |  |  |\n James | - | - | -\n- |  |  |\n  |  |\n```\n*Now I have to find the younest penguin*\n\n*In the table, there are two Gwens*\n\n```css\nName | Age (cm) | Height (cm) | Weight (kg)\n Louis | 5 | 80 | 13\n Gwen  | 5 |",
            "correct": false
        }
    ]
}