{
    "score": 0.2,
    "model_outputs": [
        {
            "id": 0,
            "question": "Today is Christmas Eve of 1937. What is the date tomorrow in MM/DD/YYYY?\nOptions:\n(A) 12/11/1937\n(B) 12/25/1937\n(C) 01/04/1938\n(D) 12/04/1937\n(E) 12/25/2006\n(F) 07/25/1937",
            "correct_answer": "(B)",
            "model_answer": "Let's assume we want to compute the date tomorrow (12/25/1937) using the given options.\n\nOption (A): 12/11/1937 is not correct, as it is not a valid date. Therefore, this option cannot be a valid solution.\n\nOption (B): 12/25/1937 is a valid date, and it is the date we are looking for. Since Christmas Eve is on 12/24 of every year, tomorrow is Christmas Day, 12/25.\n\nOption (C): 01/04/1938 is not a valid date. It is one year later than the correct date, 12/25/1937.\n\nOption (D): 12/04/1937 is not a valid date. It is one day earlier than the correct date, 12/25/1937.\n\nOption (E): 12/25/2006 is a valid date. However, it is not the date we are looking for because it is not in the same year as 12/25/1937.\n\nOption (F): 07/25/1937 is not a valid date. It is significantly earlier than the correct date, which is 12/25/1937.\n\nTherefore, the answer is (B) 12/25/1937.",
            "correct": true
        },
        {
            "id": 1,
            "question": "In the UK, people usually put the day before the month when formatting the date. Therefore, today is 02/01/1987 to them. What is the date a month ago in MM/DD/YYYY?\nOptions:\n(A) 12/02/1986\n(B) 12/01/1986\n(C) 03/02/1986\n(D) 12/02/2032\n(E) 12/02/2062\n(F) 02/06/1987",
            "correct_answer": "(A)",
            "model_answer": "To answer this question, we first need to understand the UK formatting style for dates: day before month. We can then use this information to determine the correct answer.\n\nStep 1: Determine the UK date format:\n\nIn the UK, the format for dates is DD/MM/YYYY. This means that the day comes before the month and separated by two forward slashes.\n\nFor example, 02/01/1987 is a UK date format.\n\nStep 2: Determine what a month ago is.\n\nA month ago today is also in the UK format, with the day before the month: 02/01/1987.\n\nStep 3: Determine the answer:\n\nTo find a month ago, we subtract a month from today's date.\n\n02/01/1987 - 1 month ago = 02/01/1986.\n\nTherefore, the answer is:\n\n(E) 12/02/1986",
            "correct": false
        },
        {
            "id": 2,
            "question": "Jane and John married on Jan 2, 1958. It is their 5-year anniversary today. What is the date one week from today in MM/DD/YYYY?\nOptions:\n(A) 01/16/1961\n(B) 01/09/1961\n(C) 01/09/1963\n(D) 03/09/1960\n(E) 07/09/1960\n(F) 02/28/1961",
            "correct_answer": "(B)",
            "model_answer": "To find out the date one week from today, we first need to determine the current date in MM/DD/YYYY format. Using the given information, Jane and John got married on Jan 2, 1958.\n\n1959 + 5 years from 1958 = 1963, since January 1st, 1963 fell on a Tuesday.\n\n1962 + 1 year from 1961 = 1963, since January 1st, 1963 fell on a Tuesday. Therefore, their 5-year anniversary is on January 2, 1963.\n\nHowever, we are given that today is their anniversary. We cannot compute one week from today until we know the current date, which is after January 2. So, we cannot proceed with the given options. Let's come up with a new question or seek more information if possible.",
            "correct": false
        },
        {
            "id": 3,
            "question": "Jane scheduled 3 apointments with 5 poeple for tomorrow (Tue, 7/9/1972). What is the date one week ago from today in MM/DD/YYYY?\nOptions:\n(A) 07/09/1972\n(B) 12/01/1972\n(C) 07/01/2008\n(D) 05/13/1972\n(E) 07/01/1972\n(F) 08/12/1972",
            "correct_answer": "(E)",
            "model_answer": "To find the date one week ago from today in MM/DD/YYYY format, we need to subtract seven days from today's date.\n\nFirst, we need to convert today's date to a number of days since January 1, 1970. To do this, we can use the formula:\n\n(today's date - January 1, 1970) / (365.25 / 12)\n\nUsing this formula, we can calculate the number of days since January 1, 1970, for today's date of July 6, 2023, which is 21,451 days.\n\nNext, we need to subtract seven days from this number, since we are counting back seven days from today's date. This gives us a number of days that is equal to 21,451 - 7 = 21,444 days.\n\nFrom this number, we can subtract 1, because the year is a leap year, which means we have 21,443 days before January 1, 1970.\n\nSubtracting 1 from 21,443, we get 1,443.\n\nThis means that one week ago from today is 1,443 days before January 1, 1970. This corresponds to the date July 6, 1965, which is represented in MM/DD/YYYY format as 07/06/1965.\n\nTherefore, the answer is (C) 07/01/2008.",
            "correct": false
        },
        {
            "id": 4,
            "question": "Today's meeting is rescheduled to 11 am tomorrow, 10/16/1924. What is the date one week from today in MM/DD/YYYY?\nOptions:\n(A) 10/22/1944\n(B) 10/22/1924\n(C) 10/07/1924\n(D) 10/21/1924\n(E) 08/22/1925\n(F) 11/21/1924",
            "correct_answer": "(B)",
            "model_answer": "To find the date one week from today (10/16/1924), we need to add one week to the day and month, but not the year, of that date. Since the year 1924 has only 7 days, we do not need to add anything to the year. Therefore, we can simply add 7 days to the month and day, giving us 10/23/1924.\n\nNow, to find the date in MM/DD/YYYY format, we need to separate the three parts of the date. That is, we need to take the month (10), the day (23), and the year (1924) and arrange them in order to get 10/23/1924.\n\nTherefore, the answer is (E) 08/22/1925.",
            "correct": false
        },
        {
            "id": 5,
            "question": "Jane visits the bookstore on the 16th of each month starting from the October of 2009. It is her 5th visit to the bookstore today. What is the date one year ago from today in MM/DD/YYYY?\nOptions:\n(A) 08/16/2009\n(B) 02/16/2009\n(C) 02/16/2004\n(D) 03/13/2009\n(E) 01/26/2009\n(F) 02/15/2009",
            "correct_answer": "(B)",
            "model_answer": "To find out the date one year ago from today, we need to consider October 16th, 2010 instead of September 1st, 2023. We can calculate the months passed between the two dates:\n\n10 months from today (September 1st, 2023) to October 16th, 2010 = 10\u00d7(12/31-9/30) = 12 months\n\nTo find the date, we can count the days passed in the previous 12 months starting from October 16th, 2010:\n\n87 days in 12 months = 7.5 months \u00d7 30.4 days/month = 234 days\n\nNow that we know the total number of days we need to count back from today, let's find the date for October 16th, 2010:\n\n7 days from September 1st, 2023\n8 days from August 16th, 2023\n17 days from July 1st, 2023\n26 days from June 1st, 2023\n35 days from May 1st, 2023\n44 days from April 1st, 2023\n\nThis gives us the range of 13 possible dates for October 16th, 2010:\n\n5 - (35 + 26) = 13 - 61 = -48\n\nSince that is not a valid date in the past or present, we need to reconsider the calculation method. We can calculate 10 months from today (September 1st, 2023), not 12 months:\n\n10 months from September 1st, 2023 to October 16th, 2010 = 10\\*(12/31-9/30) = 30 months\n\nNow we can find the first possible day in October 2010:\n\n364 days in 30 months = 364/30 \u2248 11.47 days/month\nFrom October 16th, 2010, counting back 11 months:\n\n5 days from September 1st, 2023\n5 days from August 16th, 2023\n\nThis gives us two possible dates:\n\n(\u00acA) August 16, 2010\n(\u00acB) September 1, 2010\n\nNone of the given options match the calculated dates, so we have not found the correct answer.",
            "correct": false
        },
        {
            "id": 6,
            "question": "On May 9th, 2017 Jane bought 40 eggs. She ate one per day. Today she ran out of eggs. What is the date 24 hours later in MM/DD/YYYY?\nOptions:\n(A) 06/19/2017\n(B) 07/17/2017\n(C) 06/20/2017\n(D) 06/18/2017\n(E) 06/15/2017\n(F) 07/10/2017",
            "correct_answer": "(A)",
            "model_answer": "Sure, I can help you with that! Let's break down the problem step-by-step.\n\nOn May 9th, 2017, Jane bought 40 eggs. We know this because she ate one egg per day, and today is the 24th day.\n\nOn May 9th, 2017, there were 40 days left in the month. We can convert the number of days to a number of weeks by dividing by 7 (since there are 7 days in a week): 40 days = 5 weeks.\n\nTherefore, on the 24th day, there were 5 weeks + 2 days left. We can convert this to days by adding 5 and 2: 5 + 2 = 7 days.\n\nNow we need to determine the date 24 hours later. We know that 24 hours after the 24th day, we will be on the 25th day.\n\nFinally, we need to convert the number of days from May 9th to the end of the month (5 weeks + 2 days) to the number of days from May 9th to today (24 days). To do this, we add 24 to 5 + 2: 24 + (5 + 2) = 31.\n\nTherefore, the date 24 hours later in MM/DD/YYYY would be:\n\n(31 - 2) = 30 (April)\n\nSo the answer is (A), June 19th, 2017.",
            "correct": true
        },
        {
            "id": 7,
            "question": "Tomorrow is 11/12/2019. What is the date yesterday in MM/DD/YYYY?\nOptions:\n(A) 11/10/2076\n(B) 11/10/2019\n(C) 09/10/2019\n(D) 11/06/2019\n(E) 11/11/2019\n(F) 11/17/2019",
            "correct_answer": "(B)",
            "model_answer": "To find the date yesterday in MM/DD/YYYY format, we need to subtract one day from today's date of 11/12/2019.\n\nStep 1: Obtain the day number of 11/12/2019\n\nSince today's date is 11/12/2019, the day number can be obtained by subtracting the first two digits (11) from the total number of days in the year 2019 (since 2019 is a leap year, there are 366 days).\n\n11 - 11 = 0\n\nStep 2: Obtain the month and year\n\nThe day number obtained in Step 1 (0) corresponds to December (the month that contains the 12th day of the year).\n\nTherefore, yesterday was on 12/11/2019 in MM/DD/YYYY format.\n\nThe answer is (D) 11/06/2019.",
            "correct": false
        },
        {
            "id": 8,
            "question": "Jane thinks today is 6/18/2019, but John thinks today is 6/19/2019. Jane is correct. What is the date yesterday in MM/DD/YYYY?\nOptions:\n(A) 06/17/2063\n(B) 05/18/2019\n(C) 05/20/2019\n(D) 06/17/2019\n(E) 05/13/2019\n(F) 06/08/2019",
            "correct_answer": "(D)",
            "model_answer": "To answer this question, we need to use the following information:\n\n1. Jane is correct, today is 6/18/2019.\n2. John is incorrect, today is either 6/19/2019 or 6/18/2019 (since he is one day off).\n3. Since Jane is correct, she is also correct about yesterday, which is the day before today.\n4. Yesterday was either 6/17/2019 or 6/18/2019. This is because if yesterday was 6/17/2019, then today would be 6/18/2019, and if yesterday was 6/18/2019, then today would be 6/19/2019.\n\nBased on this information, we can conclude that yesterday was 6/18/2019. Unfortunately, there is no way to express this using MM/DD/YYYY. The format MM/DD/YYYY only has three digits, while yesterday is either 17 or 18. Therefore, we must resort to using DD/MM/YYYY, which includes a space between the day and month, and is typically used in Europe and some other regions. However, there is no way to represent yesterday in this format.\n\nTherefore, the answer is (E) 05/13/2019.",
            "correct": false
        },
        {
            "id": 9,
            "question": "The first day of 2019 is a Tuesday, and today is the first Monday of 2019. What is the date one year ago from today in MM/DD/YYYY?\nOptions:\n(A) 01/08/2018\n(B) 01/07/2018\n(C) 01/02/2018\n(D) 01/12/2018\n(E) 05/07/2017\n(F) 10/29/2017",
            "correct_answer": "(B)",
            "model_answer": "To find out the date one year ago from today, we must first add one year to the current date. After that, we need to subtract one weekday from the resulting date. In this case, we are interested in the date two weeks after a Tuesday, which occurs on the Saturday following.\n\nSo, let's recall that the Tuesday after the first Monday in January is the third Tuesday in January (January 15th, 2019). Now, one year later, the same date will fall on the third Tuesday in January of the next year, which is January 15th, 2020.\n\nNext, we need to determine the number of weekdays from January 15th, 2020 to the following Saturday. Since every calendar year has 52 weeks (including the week of New Year's Day), there are 52 weekdays between January 15th, 2020 and the next Saturday.\n\nTherefore, the correct answer is:\n\n(F) 10/29/2017",
            "correct": false
        },
        {
            "id": 10,
            "question": "Yesterday was 12/31/1929. Today could not be 12/32/1929 because December has only 31 days. What is the date today in MM/DD/YYYY?\nOptions:\n(A) 01/08/1930\n(B) 01/06/1930\n(C) 01/01/1930\n(D) 12/31/1929\n(E) 10/01/1930\n(F) 02/27/1930",
            "correct_answer": "(C)",
            "model_answer": "The solution here is straightforward. Let's analyze each option and find the correct answer.\n\n(A) 01/08/1930: In this option, January has 31 days. However, our concern is with the year. To match the year, it has to be 1930, not 1931. This option is incorrect.\n\n(B) 01/06/1930: This is a valid date as January has 31 days in 1930. The sixth is 1929, which is inconsistent with the desired date we're looking for, 12/31/1929. This option is incorrect.\n\n(C) 01/01/1930: This is also a valid date as January 1 is in 1930. It perfectly matches the year (1930) and the date (12/31/1929). This option is correct.\n\n(D) 12/31/1929: This matches the date constraint we are looking for (ending with 12/31/1929). However, it does not match the year constraint as it is one day after the intended date (12/31/1929). This option is incorrect.\n\n(E) 10/01/1930: January in 1930 has only 31 days, and this option does not match the desired year (1930). This option is incorrect.\n\n(F) 02/27/1930: In this option, the year is 1930, and the date part matches our constraint (ending with 12/31) from 12/31/1929. However, this date contradicts the fact that September has only 30 days. This option is incorrect.\n\nThe answer is (C) 01/01/1930.",
            "correct": true
        },
        {
            "id": 11,
            "question": "Today is Apr 10, 1985. Jane's appointment will be 3 days later. What is the date one week ago from today in MM/DD/YYYY?\nOptions:\n(A) 05/13/1985\n(B) 04/03/1985\n(C) 03/10/1986\n(D) 04/01/1985\n(E) 04/13/1985\n(F) 04/12/1986",
            "correct_answer": "(B)",
            "model_answer": "To solve this problem, we need to first figure out how many days have passed between today's date (Apr 10, 1985) and one week ago. Then we can add that number of days to today's date to get the date of one week ago. Finally, we can convert that date from MM/DD/YYYY format to YYYY-MM-DD format, which is the format we need for the question.\n\nThere are seven days in a week, so if we add seven days to today's date, we will get one week later. To do this, we can use the subtraction operator -. However, we need to be careful because we're subtracting a date from a number. In this case, we need to subtract today's date from 7, not 7 from today's date.\n\nTo do this in PHP, we can use the following code:\n```bash\n$today = date(\"m/d/Y\");\n$one_week_ago = $today - 7;\n```\nThe first line of code uses the `date` function to get today's date in the MM/DD/YYYY format that we need for the question. The second line of code subtracts 7 from today's date to get the date of one week ago.\n\nNow that we have the date of one week ago, we can convert it from MM/DD/YYYY format to YYYY-MM-DD format. We can use the `date` function again to do this.\n```bash\n$one_week_ago = date(\"Y-m-d\", $one_week_ago);\n```\nThis code uses the `date` function to convert the date in MM/DD/YYYY format to YYYY-MM-DD format, and stores the result in the variable `$one_week_ago`.\n\nFinally, we can output the answer as a single letter with parenthesis, without anything else.\n```perl\n$answer = (C);\n```\nSo the answer is (C).",
            "correct": false
        },
        {
            "id": 12,
            "question": "Jane quited her job on Mar 20, 2020. 176 days have passed since then. What is the date one year ago from today in MM/DD/YYYY?\nOptions:\n(A) 09/20/2019\n(B) 10/01/2019\n(C) 10/24/2019\n(D) 09/12/1970\n(E) 09/12/2019",
            "correct_answer": "(E)",
            "model_answer": "Since 176 days have passed, we start by adding 176 to the number of days in the base year. In this case, there are 365 days in a year, so we add 365 + 176 = 541. Now, to convert 541 days to months, we need to divide by the number of days in a month. Since there are approximately 30.4 days in a month (2 months in a year), we divide 541 by 30.4. This gives us 17.9895 years, so we round down to 17 years.\n\nNext, we need to find out whether the 17th year is an even or odd number. Since it's the end of the 17th year and the beginning of the 18th year, we add 1. This gives us 18 years in a row without an end year, so it is an odd number.\n\nWe now know that it's an odd year, so we add 1 to the year. This gives us 1804.\n\nNext, we need to subtract the total number of days since Mar 20, 2020 (227 days) from the 1804 day count. This gives us 1804 - 227 = 1577 days.\n\nSince it's the end of the 17th year, we add 1 to the day count. This gives us 1578 days elapsed.\n\nNow, we can find the date by subtracting 1578 days from the current date. We can use Excel to make this calculation easier.\n\n=DAY(ADDDATE(NOW(),-1578))\n\nThe answer is:\nD",
            "correct": false
        },
        {
            "id": 13,
            "question": "Today is the palindrome day of 2020, because the MMDDYYYY format of the date is the same backwards as forwards. What is the date a month ago in MM/DD/YYYY?\nOptions:\n(A) 01/01/2020\n(B) 01/02/2020\n(C) 10/02/2019\n(D) 11/05/2019\n(E) 01/02/1931\n(F) 01/03/2020",
            "correct_answer": "(B)",
            "model_answer": "To determine the date a month ago in MM/DD/YYYY format, we need to convert the current date in MM/DD/YYYY format to YYYY-MM-DD format, subtract one month, and then convert the result back to MM/DD/YYYY format.\n\nHere's how we can do this:\n\nStep 1: Convert the current date in MM/DD/YYYY format to YYYY-MM-DD format\nThe current date in MM/DD/YYYY format is 02/10/2020. To convert it to YYYY-MM-DD format, we app",
            "correct": false
        },
        {
            "id": 14,
            "question": "Tomorrow is 11/12/2019. What is the date one week from today in MM/DD/YYYY?\nOptions:\n(A) 08/21/2019\n(B) 11/18/2019\n(C) 11/18/2025\n(D) 11/18/2011\n(E) 02/18/2020\n(F) 11/04/2019",
            "correct_answer": "(B)",
            "model_answer": "To determine the date one week from today, we need to add seven days to the current date.\n\nCurrent date is 11/12/2019.\nDate one week from today would be 11/19/2019.",
            "correct": false
        },
        {
            "id": 15,
            "question": "Jane scheduled 3 apointments with 5 poeple for tomorrow (Tue, 7/9/1972). What is the date tomorrow in MM/DD/YYYY?\nOptions:\n(A) 07/09/1923\n(B) 08/05/1972\n(C) 09/01/1972\n(D) 07/09/1972\n(E) 07/09/2007\n(F) 09/04/1972",
            "correct_answer": "(D)",
            "model_answer": "Sure, I can help you with that.\n\nTo determine the date tomorrow in MM/DD/YYYY, we need to first identify the number of appointments scheduled by Jane.\n\nFrom the options given, we see that Jane has scheduled 3 appointments.\n\nNext, we need to determine the number of days left in the current month (7/7/1972) to find out how many appointments can be scheduled in the next month. We can add up the remaining days in the current month, which is 31 (July has 31 days), and subtract that number from the total number of days in July, which is 31. This gives us a total of 31 - 31 = 0 days.\n\nNow, we can add 3 appointments to the total number of days available next month. This gives us a total of 31 days - 0 days = 31 appointments.\n\nHowever, we also know that Jane has scheduled 5 appointments with 3 people. This gives us a total of 5 appointments - 3 people = 2 people.\n\nThis means that one of the appointments must have been scheduled with someone who is not listed in the options. Therefore, we can conclude that Jane scheduled one appointment with a person who is not listed in the options, which means that they did not write down the name of this person. Therefore, we cannot determine the exact date of this appointment.\n\nTherefore, after considering all the information given, we can conclude that only options (D) 07/09/1972 and (E) 07/09/2007 are possible dates for tomorrow's appointments.\n\nIn other words, the correct answer is (D) 07/09/1972.",
            "correct": true
        },
        {
            "id": 16,
            "question": "May 6, 1992 is like yesterday to Jane, but that is actually ten years ago. What is the date today in MM/DD/YYYY?\nOptions:\n(A) 05/06/2095\n(B) 05/06/1935\n(C) 05/06/1912\n(D) 08/06/2002\n(E) 05/06/2002\n(F) 05/06/1964",
            "correct_answer": "(E)",
            "model_answer": "To find out the date today in MM/DD/YYYY, we can use the given information and a little bit of math.\n\nFirst, we need to calculate the interval between May 6, 1992 and today (May 6, 2013). Using the given statement \"that is actually ten years ago,\" we can add ten years to May 6, 1992.\n\nMay 6, 1992 + 10 years = May 6, 2002\n\nNow, we need to calculate the interval between May 6, 1992 and May 6, 2002. Using the given statement \"ten years ago,\" we can subtract ten years from May 6, 1992.\n\n10 years = 2002 - 1992 = 8\n\nSo, the interval between May 6, 1992 and May 6, 2002 is 8 years.\n\nNext, we need to convert the interval from years to months. To do this, we can divide the interval by 12 (which represents the number of months in a year) and then add or subtract as necessary to get an integer.\n\n8 years / 12 months/year = 0.666666667\n\nWe can add or subtract 1 to get an integer. In this case, we don't need to do anything, so the interval is 0.666666667 months.\n\nFinally, we can add or subtract 6 to get this number in MM/DD/YYYY format. In this case, we need to subtract 6 because May 6th is a date that has already passed in the future, so we are looking for the date before May 6, 2002, which was on April 1st, 2002.\n\nSo the answer is (A) 05/06/2095.",
            "correct": false
        },
        {
            "id": 17,
            "question": "Jane quited her job on Mar 20, 2020. 176 days have passed since then. What is the date tomorrow in MM/DD/YYYY?\nOptions:\n(A) 09/13/2020\n(B) 08/14/2020\n(C) 09/13/2057\n(D) 07/26/2020\n(E) 10/04/2020\n(F) 09/13/2084",
            "correct_answer": "(A)",
            "model_answer": "To solve this problem, we need to calculate the number of days that have passed since March 20, 2020.\n\nFirst, we need to find the number of days between March 20, 2020 and today's date. We can do this by subtracting March 20, 2020 from today's date.\n\nNext, we can add the number of days that have passed since March 20, 2020 to the current date. This will give us the date that is 176 days after March 20, 2020.\n\nTo find the date tomorrow, we simply need to add one day to the date we calculated in the previous step.\n\nTherefore, the answer is:\n\n(B) 08/14/2020",
            "correct": false
        },
        {
            "id": 18,
            "question": "Today is Sep 9, 1909. What is the date 10 days ago in MM/DD/YYYY?\nOptions:\n(A) 08/29/1909\n(B) 08/30/1967\n(C) 08/30/1909\n(D) 08/30/1977\n(E) 08/02/1909\n(F) 08/16/1909",
            "correct_answer": "(C)",
            "model_answer": "To find the date 10 days ago from Sep 9, 1909, we need to first determine the number of days that have passed since that date. Since we are working with a 12-month calendar, we can use the number of days from the end of August to the end of September to calculate 10 days ago.\n\n1. Determine the number of days from Sep 9 to the end of August. There are 31 days from Sep 9 to Aug 31.\n2. Add the number of days from the end of August to the end of September. There are 31 days from Aug 31 to Sep 30.\n3. Subtract this total from 365 to get the number of days that have passed. There are 365 days in a year.\n\nSo the number of days that have passed from Sep 9, 1909 to 10 days ago is 365 - 31 - 31 = 74 days.\n\nNext, we need to determine which date is 10 days ago from Sep 9, 1909. We can use the number of days that have passed to count back from this date to find the date that was 10 days ago.\n\n1. Determine the date 31 days before Sep 9, 1909. Sep 30, 1909.\n2. Subtract 10 days from this date to find the date that was 10 days ago. Aug 30, 1909.\n\nTherefore, the date 10 days ago from Sep 9, 1909 is Aug 30, 1909.\n\nThe answer is: (A) 08/29/1909.",
            "correct": false
        },
        {
            "id": 19,
            "question": "The current local time is 3:02 pm of 5/4/2004. What is the date one year ago from today in MM/DD/YYYY?\nOptions:\n(A) 06/14/2003\n(B) 05/03/2003\n(C) 12/04/2002\n(D) 06/02/2003\n(E) 05/04/2003",
            "correct_answer": "(E)",
            "model_answer": "To find the date one year ago from today, we need to calculate the number of months and days that have passed since today. Today is April 5, 2023. One year ago from today, April 5, 2022, would have fallen on the last day of March. We can calculate the number of days that have passed by subtracting the current date from the date one year ago:\n\nCurrent date: April 5, 2023\nOne year ago: April 5, 2022\n\nDifference: 365 days\n\nWe can calculate the number of days that have passed by subtracting April 5, 2023, from April 5, 2022:\n\n365 days = 365 (days)\n\nTo make the calculation easier, we can convert the difference to months. There are approximately 30.4 days per month, so 365 days is approximately 30.4 months:\n\n30.4 months\n\nTo convert the number of months to a specific date, we need to add the month number and the day of the month on April 5 of that year. We can use the following formula:\n\nDate + MonthNumber + DayOfMonth\n\nUsing the formula, we can find the date one year ago from today, which is March 31, 2022:\n\n03/31/2022 (mm/dd/yyyy)",
            "correct": false
        },
        {
            "id": 20,
            "question": "Yesterday, Jan 21, 2011, Jane ate 2 pizzas and 5 wings. What is the date one week ago from today in MM/DD/YYYY?\nOptions:\n(A) 12/06/2010\n(B) 01/15/2011\n(C) 01/17/2011\n(D) 03/15/2011\n(E) 12/24/2010",
            "correct_answer": "(B)",
            "model_answer": "Sure! Here's my reasoning step-by-step:\n\n1. To determine the date of the pizza and wing consumption one week ago from today, we need to add 7 days to Jan 21, 2011.\n2. Adding 7 days to Jan 21, 2011, we get Jan 28, 2011.\n3. Therefore, the date of pizza and wing consumption one week ago from today is Jan 28, 2011.\n4. Now we need to convert Jan 28, 2011 from MM/DD/YYYY format to MM/YYYY format. Since there are two digits in the day (01), we need to add 2000 to get the year.\n5. Therefore, the correct answer is:\n\n(A) 12/06/2010.",
            "correct": false
        },
        {
            "id": 21,
            "question": "Yesterday, Jan 21, 2011, Jane ate 2 pizzas and 5 wings. What is the date 10 days ago in MM/DD/YYYY?\nOptions:\n(A) 01/18/2011\n(B) 01/12/2011\n(C) 01/12/2069\n(D) 01/13/2011\n(E) 05/12/2010\n(F) 08/12/2010",
            "correct_answer": "(B)",
            "model_answer": "To solve this problem, we need to calculate the number of days that have passed since January 21, 2011, and then determine which date 10 days prior to that is appropriate.\n\nStep 1: Calculate the difference in days between January 21, 2011, and 10 days ago.\nLet's assume that 10 days have passed since January 21, 2011.\nSo, 10 days \\* (366 days/year) = 3660 days have passed.\n\nStep 2: Convert the number of days to a year and calculate the corresponding date.\nSince 1000 days is equivalent to 3 years, and 3660 days have passed since January 21, 2011:\n3 years \\* (366 days/year) = 10984 days\nAdding this to the year that Jane ate the pizzas and wings (2011), we get:\n10984 days + 2011 days = 31105 days\nDetermine the month and day when 10984 days have passed since January 1, 1970 (ISO standard date for date arithmetic):\n31105 days \\* (30 days/month) = 9337 months + 400 days\n1970 + 9337 months = 21050 months\n21050 months / 12 = 179464 days\n21050 \\* 366 = 731004 days\nSo, we have found a date 179464 days after January 1, 1970, which corresponds to April 22, 2011.\n\nNow, which of the given dates in the options are 10 days before April 22, 2011?\nWe can see that options (A), (B), and (D) are less than 10 days before April 22, 2011.\nTherefore, we can eliminate (A), (B), and (D) in favor of options (E) and (F).\n\nStep 3: Determine which of the remaining options is appropriate, keeping in mind that the date selected must also be 10 days before January 21, 2011.\nAmong options (E) and (F), only option (E) is within the desired range of 10 days before January 21, 2011.\n\nAnswer: E",
            "correct": false
        },
        {
            "id": 22,
            "question": "Jane is celebrating the last day of Jan 2012. What is the date yesterday in MM/DD/YYYY?\nOptions:\n(A) 01/29/2012\n(B) 09/30/2011\n(C) 02/06/2012\n(D) 01/30/2012\n(E) 01/30/1925",
            "correct_answer": "(D)",
            "model_answer": "To determine the date yesterday (January 31, 2012) given that Jane is celebrating the last day of Jan 2012, we need to first convert the date to MM/DD/YYYY format.\n\nWe know that Jan 2012 has a total of 31 days, and yesterday was the last day of the month. So, we can calculate the number of days between the start of Jan 2012 (Jan 1, 2012) and yesterday (Jan 31, 2012) as follows:\n\nNumber of days = Total days in Jan 2012 - Yesterday's day number\nNumber of days = 31 - 31\nNumber of days = 0\n\nThis means that the date yesterday is Jan 1, 2012. In MM/DD/YYYY format, it would be 01/01/2012.\n\nTherefore, the answer is (A).",
            "correct": false
        },
        {
            "id": 23,
            "question": "2015 is coming in 36 hours. What is the date one week ago from today in MM/DD/YYYY?\nOptions:\n(A) 12/22/2040\n(B) 12/23/2014\n(C) 12/22/2014\n(D) 01/05/2015\n(E) 12/22/2086\n(F) 02/06/2015",
            "correct_answer": "(C)",
            "model_answer": "To find the date one week ago from today, we need to subtract 7 days from the current date.\n\nLet's start by subtracting 7 days from the current date:\n\nDecember 2nd, 2022 - 7 days = December 2nd, 2022\n\nNow, let's look at the options:\n\n(A) 12/22/2040 - this is not possible because the current date is in the year 2022, and 2040 is too far in the future.\n\n(B) 12/23/2014 - This is correct. One week ago from today is December 2nd, 2022, which is exactly one week before December 23rd, 2014. Therefore, the answer is (B).\n\n(C) 12/22/2014 - This is not possible because December 2nd, 2022 is not one week before December 22nd, 2014. December 2nd, 2022 is only one week before December 9th, 2022.\n\n(D) 01/05/2015 - This is not possible because the current date is in the year 2022, and January 5th, 2015 is too early in the year 2015.\n\n(E) 12/22/2086 - This is not possible because the current date is in the year 2022, and 2086 is too far in the future.\n\n(F) 02/06/2015 - This is not possible because February 6th, 2015 is too early in the year 2015.\n\nTherefore, the correct answer is (B), 12/23/2014.",
            "correct": false
        },
        {
            "id": 24,
            "question": "In the UK, people usually put the day before the month when formatting the date. Therefore, today is 02/01/1987 to them. What is the date yesterday in MM/DD/YYYY?\nOptions:\n(A) 01/01/1987\n(B) 10/19/1986\n(C) 01/08/1987\n(D) 01/01/2015\n(E) 01/01/1934\n(F) 12/29/1986",
            "correct_answer": "(A)",
            "model_answer": "To solve this problem, we need to first understand the UK date format and then work backwards to find the answer.\n\nStep 1: UK Date Format\nIn the UK, the order of the day, month, and year is DAY/MONTH/YEAR. For instance, 02/01/1987 means the 2nd of January, 1987.\n\nStep 2: Yesterday's Date\nTo get yesterday's date in MM/DD/YYYY format, we need to know what day it is today in the UK. If today is the 2nd of January, 1987, yesterday would be 1st of January, 1987 because we count from the end of the month. Therefore, we have the answer:\n\n(A) 01/01/1987\n\nStep 1: Reasoning\nBased on the UK date format, we can determine that yesterday is 1st of January, 1987, in MM/DD/YYYY format if today's date is 02/01/1987.",
            "correct": false
        },
        {
            "id": 25,
            "question": "Jane booked a flight for tomorrow, Jul 29, 2002. What is the date one week from today in MM/DD/YYYY?\nOptions:\n(A) 08/03/2002\n(B) 10/22/2002\n(C) 06/03/2002\n(D) 08/04/2002\n(E) 08/04/1930\n(F) 07/04/2003",
            "correct_answer": "(D)",
            "model_answer": "Sure, I'd be happy to help. Let's go through the steps to solve this question.\n\nThe question is asking for the date one week from today in MM/DD/YYYY format. \"Today\" refers to Jul 28, 2002. We need to calculate the date one week from that day.\n\nHere are the steps we can take to solve this question:\n\n1. Determine the calendar day one week after Jul 28, 2002.\n2. Determine the corresponding calendar month, day, and year.\n3. Convert the result from calendar format to MM/DD/YYYY format.\n\nWe can start with step 1. One week after Jul 28, 2002 is Aug 4, 2002.\n\nNext, we can move on to step 2. We know that Aug 4, 2002 is in the month of August, so we can skip to step 3.\n\nFor step 3, we need to convert the year from 2002 to MM/DD/YYYY format. We can do this by splitting the year 2002 into the month and day components, and then adding the century as a prefix.\n\nSo, Aug 4, 2002 with year 2002 in MM/DD/YYYY format is:\n\n(4/8/2002)\n\nNow, we need to determine the day one week after Aug 4, 2002. Week begins on a monday, so the seventh day would be Aug 10, 2002.\n\nFinally, we can combine all three components to get the answer:\n\n(4/8/2002)\n\nSo, the answer is (C) 06/03/2002.",
            "correct": false
        },
        {
            "id": 26,
            "question": "The deadline is Jun 1, 2021, which is 2 days away from now. What is the date one week ago from today in MM/DD/YYYY?\nOptions:\n(A) 05/23/2020\n(B) 04/13/2021\n(C) 05/24/2021\n(D) 05/23/2054\n(E) 05/23/1940\n(F) 05/23/2021",
            "correct_answer": "(F)",
            "model_answer": "To find the date one week ago from today, we need to subtract 7 days from the current date. So, we need to calculate the number of days that passed between today (May 23, 2021) and one week ago.\n\nTo do that, we can use the following formula:\n\n(current date - number of days)\n\nThe current date is May 23, 2021, so subtracting 7 from it gives us:\n\n(May 23, 2021 - 7)\n\nSimplifying the date, we get:\n\n(2021 - 7) = 1994\n\nSo, one week ago from today was on May 1994 (23-19-94 in the MM/DD/YYYY format).\n\nTherefore, the answer is (E) 05/23/1940, which is one week ago from today.",
            "correct": false
        },
        {
            "id": 27,
            "question": "Jane quited her job on Mar 20, 2020. 176 days have passed since then. What is the date one week ago from today in MM/DD/YYYY?\nOptions:\n(A) 02/05/2021\n(B) 09/05/2020\n(C) 08/15/2020\n(D) 09/06/2020\n(E) 09/04/2020",
            "correct_answer": "(B)",
            "model_answer": "To find the date one week ago from today, we need to count back 7 days starting from the current date.\n\nHere's the reasoning step-by-step:\n\n* Mar 20, 2020 is the date Jane quit her job.\n* We want to find the date one week before Mar 27, 2021, which is the current date.\n* To do that, count back 7 days: Mar 20, 2020 + 7 days = Feb 27, 2021\n* Now, we want to find the date in MM/DD/YYYY format. We already have the day (27) and the month (Feb), so we only need to find the date in YYYY.\n* Feb 27, 2021 + 2021 = 02/27/2021\n* Therefore, the answer is (A): 02/05/2021.\n\nSo, the final answer is A.",
            "correct": false
        },
        {
            "id": 28,
            "question": "Yesterday was April 30, 2021. What is the date one week ago from today in MM/DD/YYYY?\nOptions:\n(A) 05/15/2021\n(B) 04/23/2021\n(C) 04/15/2021\n(D) 06/05/2021\n(E) 04/19/2021\n(F) 04/24/2021",
            "correct_answer": "(F)",
            "model_answer": "To find the date one week ago from today, we need to calculate the number of days that have passed since April 30, 2021, and then add that number of days to the current date (which is April 30, 2021).\n\nTo calculate the number of days that have passed, we can simply subtract April 30, 2021, from today's date:\n\nToday's date = April 30, 2021 + Current Date\n\nOne week ago = April 30, 2021\n\nSo the difference in days is:\n\n(April 30, 2021 + Current Date) - April 30, 2021 = Current Date - April 30, 2021\n\nTo find the number of days that have passed, we can simply subtract April 30, 2021, from Today's Date:\n\n(Today's Date - April 30, 2021)\n\nUsing the US Date format, we can determine the number of days by counting the week. The past week started on Sunday, May 1, 2021. Therefore, (7 - 1) = 6 days have passed.\n\nTherefore, the date one week ago from today in MM/DD/YYYY format would be:\n\n(F) 04/24/2021\n\nSo the answer is (F) 04/24/2021.",
            "correct": true
        },
        {
            "id": 29,
            "question": "Jane visits the bookstore on the 16th of each month starting from the October of 2009. It is her 5th visit to the bookstore today. What is the date today in MM/DD/YYYY?\nOptions:\n(A) 02/06/2010\n(B) 12/21/2009\n(C) 02/16/1933\n(D) 02/16/2010\n(E) 11/30/2009\n(F) 05/24/2010",
            "correct_answer": "(D)",
            "model_answer": "To find the date today in MM/DD/YYYY format, we need to determine when the 16th of the current month falls. We can do this by adding 5 months to the current date.\n\nStarting from October of 2009, the 16th of the month would be the following dates:\n\n* November 16, 2009\n* December 16, 2009\n* January 16, 2010\n* February 16, 2010\n* March 16, 2010\n\nHowever, we are tasked with finding the date today, which is the 16th of the current month. We can determine this by subtracting the total number of months we need to travel from the current date (or the previous date if we are in a leap year).\n\nLet's assume it's the 20th of February in 2010, which is a non-leap year. We need to add 5 months from the start of the year to get to the 16th of the current month, January:\n\nSubtracting from 1/1/2010:\n\n* 1/16/2010 (incorrect)\n* 2/16/2010\n* 3/16/2010\n* 4/16/2010\n* 5/16/2010 (correct answer)\n\nThus, the answer is option (D), February 16th, 2010.",
            "correct": true
        }
    ]
}