{
    "score": 0.06666666666666667,
    "model_outputs": [
        {
            "id": 0,
            "question": "This SVG path element <path d=\"M 55.57,80.69 L 57.38,65.80 M 57.38,65.80 L 48.90,57.46 M 48.90,57.46 L 45.58,47.78 M 45.58,47.78 L 53.25,36.07 L 66.29,48.90 L 78.69,61.09 L 55.57,80.69\"/> draws a\nOptions:\n(A) circle\n(B) heptagon\n(C) hexagon\n(D) kite\n(E) line\n(F) octagon\n(G) pentagon\n(H) rectangle\n(I) sector\n(J) triangle",
            "correct_answer": "(B)",
            "model_answer": "Answer: Choice (E) line\n\nExplanation:\n\n1. The 'd' attribute of the <path> element contains a series of 'M' (move to) and 'L' (line to) commands, which define the path of the element.\n2. The 'M' commands represent the start of a new sub-path, and they are used to move the pen to a specific point.\n3. The 'L' commands represent a line segment, and they are used to draw the path.\n4. The sequence of 'L' commands in the 'd' attribute define a series of connected line segments.\n5. The overall shape formed by the connected line segments is a line.\n\nSo, the answer is Choice (E) line.",
            "correct": false
        },
        {
            "id": 1,
            "question": "This SVG path element <path d=\"M 30.17,45.97 L 58.79,40.36 L 18.10,15.70 M 18.10,15.70 L 30.17,45.97\"/> draws a\nOptions:\n(A) circle\n(B) heptagon\n(C) hexagon\n(D) kite\n(E) line\n(F) octagon\n(G) pentagon\n(H) rectangle\n(I) sector\n(J) triangle",
            "correct_answer": "(J)",
            "model_answer": "To determine which shape is formed by the SVG path element, we need to look at the path data \"d\" attribute. The \"d\" attribute defines a series of instructions for drawing the shape. These instructions are known as the Path Data Grammar, and they consist of a series of letters and symbols that specify the shape's geometry.\n\nThe instructions in the path data \"d\" attribute for the given SVG path element are:\n\nM 30.17,45.97 L 58.79,40.36 L 18.10,15.70\nM 18.10,15.70\n\nThe M instruction stands for \"move to\", and it specifies a new starting point for the drawing. The L instruction stands for \"line to\", and it specifies a line connecting the current point to a new point.\n\nFrom the path data instructions, we can see that the drawing starts at point (30.17, 45.97), moves to point (58.79, 40.36), and then to point (18.10, 15.70). Then it moves back to point (18.10, 15.70).\n\nThe shape that is formed by these points is a\n\n(A) Line segment. The points (30.17, 45.97), (58.79, 40.36), (18.10, 15.70), and (18.10, 15.70) form a line segment.",
            "correct": false
        },
        {
            "id": 2,
            "question": "This SVG path element <path d=\"M 21.10,97.94 L 22.14,97.44 L 10.48,73.34 L 9.43,73.84 L 21.10,97.94\"/> draws a\nOptions:\n(A) circle\n(B) heptagon\n(C) hexagon\n(D) kite\n(E) line\n(F) octagon\n(G) pentagon\n(H) rectangle\n(I) sector\n(J) triangle\n(K) trapezoid",
            "correct_answer": "(K)",
            "model_answer": "Based on the given SVG path element, we can infer that it draws a polyatomic shape with straight lines. It is not a circle (option A) because it has sharp corners and straight lines. It is also not a hexagon (option C), heptagon (option B), octagon (option F), or pentagon (option G) because it does not have the correct number of sides.\n\nLet's break down the path element's attributes:\n```sql\nM 21.10,97.94\n```\nThis move command (M) moves the starting point to the coordinates (21.10, 97.94).\n```csharp\nL 22.14,97.44\nL 10.48,73.34\nL 9.43,73.84\nL 21.10,97.94\n```\nThese are four line commands (L) specifying the endpoints of the lines:\n\n1. (22.14, 97.44)\n2. (10.48, 73.34)\n3. (9.43, 73.84)\n4. (21.10, 97.94)\n\nTherefore, based on the shape's characteristics, it is a sector (option I) that encompasses a portion of a circle and two straight lines. The answer is:\n\n(I) sector.",
            "correct": false
        },
        {
            "id": 3,
            "question": "This SVG path element <path d=\"M 12.64,60.32 L 16.36,27.35\"/> draws a\nOptions:\n(A) circle\n(B) heptagon\n(C) hexagon\n(D) kite\n(E) line\n(F) octagon\n(G) pentagon\n(H) rectangle\n(I) sector\n(J) triangle",
            "correct_answer": "(E)",
            "model_answer": "To analyze this SVG path element <path d=\"M 12.64,60.32 L 16.36,27.35\"/> and determine what shape it draws, we need to examine the \"d\" attribute of the path element, which contains a string of coordinates that define the shape. The \"d\" attribute stands for \"path data\" and it is used to specify the geometry of the shape.\n\nThe \"d\" attribute in this case contains two coordinates separated by \"L\" letter. The first coordinate is \"M 12.64,60.32\" which stands for \"moveto\" 12.64 units on the x-axis and 60.32  units on the y-axis. The second coordinate is \"L 16.36,27.35\" which stands for \"lineto\" 16.36 units on the x-axis and 27.35 units on the y-axis.\n\nFrom these coordinates, we can determine that this SVG path element draws a (E) line. The \"M\" and \"L\" commands indicate the start and end of a line segment in the SVG element.",
            "correct": true
        },
        {
            "id": 4,
            "question": "This SVG path element <path d=\"M 90.54,84.19 L 72.03,34.41 L 33.90,48.59 M 33.90,48.59 L 52.41,98.37 M 52.41,98.37 L 90.54,84.19\"/> draws a\nOptions:\n(A) circle\n(B) heptagon\n(C) hexagon\n(D) kite\n(E) line\n(F) octagon\n(G) pentagon\n(H) rectangle\n(I) sector\n(J) triangle\n(K) trapezoid",
            "correct_answer": "(K)",
            "model_answer": "To determine the shape created by the SVG path element, we need to examine the sequence of points it describes. We can break down the path data into segments, where each segment corresponds to a distinct JSON path command (M for moveto, L for lineto, and H for closepath). These commands define the boundaries of segments, where a command can appear more than once in the JSON path data (M or Z may appear multiple times, while H may only appear once).\n\nWe'll start by breaking down the path data into segments. In this case, we have the following segments:\nM 90.54,84.19 L 72.03,34.41 M 33.90,48.59 M 33.90,48.59 L 52.41,98.37 M 52.41,98.37 L 90.54,84.19\n\nNow let's analyze each segment:\n\nSegment 1 (M 90.54,84.19):\nM stands for moveto. This segment starts a new sub-path, so there's no previous segment to consider. Given the co-ordinates (90.54,84.19), we'll draw an initial point at these coordinates, without specifying a specific shape yet. However, we'll keep note of it, as it could be relevant for subsequent polygons.\n\nSegment 2 (L 72.03,34.41):\nHere comes the first lineto command after the opening moveto command (or the first command in an unclosed sub-path). Given the coordinates (72.03,34.41), it seems we're starting to draw a new shape. However, as it's just one co-ordinate pair, it's difficult to determine the final shape yet.\n\nSegment 3 (M 33.90,48.59):\nAnother moveto command, which doesn't relate to any previous endpoint. Keeping in mind the endpoint co-ordinates (33.90,48.59).\n\nSegment 4 (M 33.90,48.59):\nIt's the same point as in Segment 3, but with the same lineto/curveto after this point it seems we're backtracking to close a previous path. Since our last path segment was Segment 2, let's check if we can use these points to close the figure:\n\nSegment 2 and 4 co-ordinates (72.03,34.41) and (33.90,48.59) respectively, when connected, draw a line segment, allowing us to check if these points can close the figure. If there's a corresponding moveto command with an opposite command (H or Z) that closes the path after them, we can check if this segment",
            "correct": false
        },
        {
            "id": 5,
            "question": "This SVG path element <path d=\"M 2.10,61.72 L 38.86,44.98 M 38.86,44.98 L 65.79,63.32 L 39.63,11.62 L 21.25,37.04 M 21.25,37.04 L 31.13,38.33 L 2.10,61.72\"/> draws a\nOptions:\n(A) circle\n(B) heptagon\n(C) hexagon\n(D) kite\n(E) line\n(F) octagon\n(G) pentagon\n(H) rectangle\n(I) sector\n(J) triangle",
            "correct_answer": "(C)",
            "model_answer": "To determine the type of shape drawn by the given SVG path element, we need to analyze the vertices (corners) of the shape and the lines connecting them. Let's break down the path element step by step:\n```sql\nM 2.10,61.72 L 38.86,44.98\nM 38.86,44.98 L 65.79,63.32\nM 65.79,63.32 L 39.63,11.62\nM 39.63,11.62 L 21.25,37.04\nM 21.25,37.04 L 31.13,38.33\nM 31.13,38.33 L 2.10,61.72\n```\nWe can lay down the vertices in a table:\n\n| Vertex | x-coordinate | y-coordinate |\n| --- | --- | --- |\n| A | 2.10 | 61.72 |\n| B | 38.86 | 44.98 |\n| C | 65.79 | 63.32 |\n| D | 39.63 | 11.62 |\n| E | 21.25 | 37.04 |\n| F | 31.13 | 38.33 |\n| G | 2.10 | 61.72 |\n\nUsing a graph editor like Geogebra or a drawing tool, you can draw the shape on a grid and connect the dots to see the overall structure.\n\nBased on the points, we can see that the vertices A, E, F, and G form a closed shape. The vertices B, C, and D do not lie on the same line, so they cannot form a side of a basic shape like a rectangle.\n\nLet's analyze the vertices A, E, F, and G as an example to understand the property of this shape. A, E, F, and G form a closed shape with \"corners\" having the following coordinates:\n\n* A (2.10, 61.72)\n* E (21.25, 37.04)\n* F (31.13, 38.33)\n* G (2.10, 61.72)\n\nIf we draw lines connecting the vertices in this order, we get an almost circular pattern with the vertices spread across the shape:\n```javascript\nA - E - F - G\n```\nNow, lay down the vertices in a more readable form with an edge length of 1 unit:\n```lua\nA (2.10, 61.72)           E (21.25, 37.04)\nB (38.86, 44.98)        C (65.79, 63.32)\nD (39.63, 11.62)\n```\nNow, we can see that vertices A, E, F, and G are almost on the circumference of a circle, but not exactly. Given the vertices A, E, F, and G don't fall exactly on the circumference of a circle:\n\n* |AEFG| = 84.36 < 87.87 |BCDA|, where BC=49.64 and DA=48.74.\n* |O=C C=49.64, D=48.74|O=C C=84.36, D= |BCDA|, where BC=49.64 and DA=48.74.\n* |BCDA| = 87.87 < 87.87 |BCDA|, where BC=49.64 and DA=48.74.\n\nSo, this \"almost-circle\" property of the shape with more vertices closer to the edge of a \"true\" circle neither qualifies it for a perfect circle nor",
            "correct": false
        },
        {
            "id": 6,
            "question": "This SVG path element <path d=\"M 52.00,72.00 L 3.00,95.00 L 53.00,30.00 L 52.00,72.00\"/> draws a\nOptions:\n(A) circle\n(B) heptagon\n(C) hexagon\n(D) kite\n(E) line\n(F) octagon\n(G) pentagon\n(H) rectangle\n(I) sector\n(J) triangle",
            "correct_answer": "(J)",
            "model_answer": "To analyze this SVG path element, we need to break it down into smaller parts. Let's do that:\n\n1. The `d` attribute in the `<path>` element defines the shape. It represents a directed graph of the path, where the letters `M` or `m` for MoveTo, `L` or `l` for LineTo, `H` or `h` for CurveTo, `V` or `v` for Cubic Bezier CurveTo, `C` or `c` for Cubic Bezier CurveTo, `S` or `s` for Cubic Bezier CurveTo, `Q` or `q` for Quadratic Bezier CurveTo and `T` or `t` for Smooth Cubic CurveTo are used.\n2. The `d` attribute value consists of several `L` letters, which stands for LineTo, indicating that this shape is formed by lines connecting points.\n3. Let's identify the points mentioned in the `d` attribute value:\n\t* M 52.00,72.00: Move to point (52, 72).\n\t* L 3.00,95.00: Line to point (3, 95).\n\t* L 53.00,30.00: Line to point (53, 30).\n\t* L 52.00,72.00: Line to point (52, 72).\n4. Since the shape consists of only four lines connecting the points, it is either a line segment or a quadrilateral.\n5. A quadrilateral has four sides or lines, and these sides or lines can form different shapes, such as a square, pentagon, hexagon, octagon, etc. depending on their length and the angles between them. In this case, the quadrilateral has two adjacent sides with length 52 and two adjacent sides with length 3. Therefore, it is not a square or a pentagon.\n6. A hexagon has six sides, so it is not a hexagon.\n7. A kite has two adjacent sides that are of different lengths. In this case, there are no two adjacent sides with different lengths, so it is not a kite.\n8. A sector is a portion of a circle. However, since this shape is defined by lines, it is not a sector.\n9. The shape is not a triangle, since it has four sides.\n10. The shape is not a rectangle, since it has two adjacent sides with different lengths.\n11. So, the answer must be (D) kite, since it has two adjacent sides with different lengths. However, we found that it is not a kite, since the lines that form this shape have the same length.\n\nTherefore, the an",
            "correct": false
        },
        {
            "id": 7,
            "question": "This SVG path element <path d=\"M 4.12,72.94 L 38.85,35.38 M 38.85,35.38 L 50.28,77.12 L 30.89,80.59 M 30.89,80.59 L 31.43,90.13 L 22.93,92.01 M 22.93,92.01 L 4.12,72.94\"/> draws a\nOptions:\n(A) circle\n(B) heptagon\n(C) hexagon\n(D) kite\n(E) line\n(F) octagon\n(G) pentagon\n(H) rectangle\n(I) sector\n(J) triangle",
            "correct_answer": "(C)",
            "model_answer": "Instead of giving you the answer, I will guide you on how to figure out the answer.\n\nNow, you can try to figure out the path yourself or you can use a tool such as an SVG path viewer online.\n\n* Try to take a look at the path element and see what it is describing.\n* Look for the \"M\" (moveto) commands which will start a new sub-path.\n* Look for the \"L\" (lineto) commands which will draw a line.\n* Look for the \"Z\" (closepath) command which will close the path.\n* Look for any \"H\" or \"V\" commands which will draw a horizontal or vertical line segment.\n* Try to connect the points by eye to see if you can figure out what it is describing.\n\nThis should help you figure out what the SVG path element is describing.\n\n(D) kite",
            "correct": false
        },
        {
            "id": 8,
            "question": "This SVG path element <path d=\"M 22.06,65.18 L 22.58,64.52 L 7.52,52.61 L 7.00,53.26 L 22.06,65.18\"/> draws a\nOptions:\n(A) circle\n(B) heptagon\n(C) hexagon\n(D) kite\n(E) line\n(F) octagon\n(G) pentagon\n(H) rectangle\n(I) sector\n(J) triangle\n(K) trapezoid",
            "correct_answer": "(K)",
            "model_answer": "The answer is (E) line.\n\nIn order to explain my reasoning step-by-step:\n\n1. The first segment of the `d` attribute \"M 22.06,65.18\" specifies the start point of the path as a move-to-point operation, which is a single point at the coordinates (22.06, 65.18).\n2. The second segment of the `d` attribute \"L 22.58,64.52\" specifies a line segment that starts at the previous point and ends at a point with coordinates (22.58, 64.52).\n3. The third segment of the `d` attribute \"L 7.52,52.61\" specifies a second line segment that starts at the previous point (22.58, 64.52) and ends at a point with coordinates (7.52, 52.61).\n4. The fourth segment of the `d` attribute \"L 7.00,53.26\" specifies a third line segment that starts at the previous point (7.52, 52.61) and ends at a point with coordinates (7.00, 53.26).\n5. The fifth segment of the `d` attribute \"L 22.06,65.18\" specifies a fourth line segment that starts at the previous point (7.00, 53.26) and ends at a point that coincides with the initial point (22.06, 65.18), making the path close on itself.\n\nSince the path consists of only line segments and closes on itself, it forms a closed line, which is the answer option (E) line.",
            "correct": false
        },
        {
            "id": 9,
            "question": "This SVG path element <path d=\"M 76.00,30.00 L 58.00,25.00 L 42.00,26.00 L 41.00,41.00 L 47.00,54.00 L 76.00,30.00\"/> draws a\nOptions:\n(A) circle\n(B) heptagon\n(C) hexagon\n(D) kite\n(E) line\n(F) octagon\n(G) pentagon\n(H) rectangle\n(I) sector\n(J) triangle",
            "correct_answer": "(G)",
            "model_answer": "The path element draws a triangle.\n\nMy reasoning is as follows:\n\n* I look at the starting and ending points of the path element (76.00,30.00 and 76.00,30.00). These points are the same, which implies that the path element forms a shape that starts and ends at these points.\n* I look at the intermediate points (58.00,25.00, 42.00,26.00, 41.00,41.00, 47.00,54.00). These points form a sequence of straight line segments, which implies that the shape drawn by the path element is a series of straight line segments.\n* The shape formed by a series of straight line segments is likely to be a triangle.\n* I look at the other options and rule them out: a circle would have a center point and radiating line segments; a heptagon, hexagon, octagon, pentagon, and sector would have more than three sides; a rectangle would have four right angles; a line would have only one point.\n* Therefore, the shape drawn by the path element is a triangle.",
            "correct": false
        },
        {
            "id": 10,
            "question": "This SVG path element <path d=\"M 49.47,26.27 L 55.28,65.93 L 48.51,77.47 M 48.51,77.47 L 34.78,81.76 L 36.76,67.00 M 36.76,67.00 L 14.38,76.83 M 14.38,76.83 L 49.47,26.27\"/> draws a\nOptions:\n(A) circle\n(B) heptagon\n(C) hexagon\n(D) kite\n(E) line\n(F) octagon\n(G) pentagon\n(H) rectangle\n(I) sector\n(J) triangle",
            "correct_answer": "(C)",
            "model_answer": "The SVG path element <path d=\"M 49.47,26.27 L 55.28,65.93 L 48.51,77.47 M 48.51,77.47 L 34.78,81.76 L 36.76,67.00 M 36.76,67.00 L 14.38,76.83 M 14.38,76.83 L 49.47,26.27;\"> draws a\n\nA\n\nLet's break down the path data in the SVG element:\n\nM: Stands for \"moveto\" and indicates the start of a new subpath.\n49.47,26.27: These coordinates define the starting point of the subpath.\nL: Stands for \"lineto\" and indicates that the subpath will contain a straight line segment.\n55.28,65.93: These coordinates define the end point of the first line segment.\n48.51,77.47: These coordinates define the end point of the second line segment.\nM: Indicates the start of a new subpath.\n48.51,77.47: These coordinates define the starting point of the subpath.\nL: Indicates the start of a line segment in the subpath.\n34.78,81.76: These coordinates define the end point of the line segment.\nL: Indicates the start of another line segment in the subpath.\n36.76,67.00: These coordinates define the end point of this line segment.\nM: Indicates the start of another subpath.\n36.76,67.00: These coordinates define the starting point of the subpath.\nL: Indicates the start of a line segment in the subpath.\n14.38,76.83: These coordinates define the end point of the line segment.\nM: Indicates the start of another subpath.\n14.38,76.83: These coordinates define the starting point of the subpath.\nL: Indicates the start of a line segment in the subpath.\n49.47,26.27: These coordinates define the end point of the line segment, which is also the same as the starting point of the first subpath.\n\nThe path data consists of a series of linear segments that form a closed shape. Specifically, it creates a traversal of a hexagon, as the path starts and ends at the same point, and traverses six sides in between.\n\nTherefore, the answer is hexagon.",
            "correct": false
        },
        {
            "id": 11,
            "question": "This SVG path element <path d=\"M 5.41,37.88 L 1.69,19.06 M 1.69,19.06 L 0.30,43.85 M 0.30,43.85 L 5.41,37.88\"/> draws a\nOptions:\n(A) circle\n(B) heptagon\n(C) hexagon\n(D) kite\n(E) line\n(F) octagon\n(G) pentagon\n(H) rectangle\n(I) sector\n(J) triangle",
            "correct_answer": "(J)",
            "model_answer": "(A) circle",
            "correct": false
        },
        {
            "id": 12,
            "question": "This SVG path element <path d=\"M 22.34,17.53 A 19.21,19.21 220.48 1,0 51.57,42.47 A 19.21,19.21 220.48 1,0 22.34,17.53\"/> draws a\nOptions:\n(A) circle\n(B) heptagon\n(C) hexagon\n(D) kite\n(E) line\n(F) octagon\n(G) pentagon\n(H) rectangle\n(I) sector\n(J) triangle\n(K) ellipse",
            "correct_answer": "(K)",
            "model_answer": "The given SVG path element does not draw a simple geometric shape like a circle, square, or triangle. Let's break down the path data to see what kind of shape it draws.\n```lua\nM 22.34,17.53     (0)\nA 19.21,19.21     (1)\n220.48,1,0         (2)\n51.57,42.47       (3)\nA 19.21,19.21     (4)\n220.48,1,0         (5)\n22.34,17.53       (6)\n```\nIn (1), a cubic Bezier curve starts at point (22.34, 17.53), follows the control point (14.24, 17.53), and ends at point (14.24, 10.36), creating a steep turn in the path.\n\nIn (3), the path continues with a cubic Bezier curve starting at point (14.24, 10.36), following the control point (7.44, 7.6), and ends at point (7.44, 24.57), creating a sharp turn in the opposite direction.\n\nIn (5), the last cubic Bezier curve starts at point (7.44, 24.57), follows the control point (10.44, 31.73), and ends at point (10.44, 31.73), closing the path with a segment almost collinear with the previous segment, which may create a \"bar\" shape.\n\nThere's insufficient information to determine the shape without rendering the SVG image.",
            "correct": false
        },
        {
            "id": 13,
            "question": "This SVG path element <path d=\"M 65.00,42.00 A 21.00,21.00 0.00 1,0 23.00,42.00 A 21.00,21.00 0.00 1,0 65.00,42.00\"/> draws a\nOptions:\n(A) circle\n(B) heptagon\n(C) hexagon\n(D) kite\n(E) line\n(F) octagon\n(G) pentagon\n(H) rectangle\n(I) sector\n(J) triangle\n(K) ellipse",
            "correct_answer": "(K)",
            "model_answer": "(A) circle",
            "correct": false
        },
        {
            "id": 14,
            "question": "This SVG path element <path d=\"M 4.70,85.15 L 2.36,37.14 L 18.76,36.34 M 18.76,36.34 L 21.10,84.35 L 4.70,85.15\"/> draws a\nOptions:\n(A) circle\n(B) heptagon\n(C) hexagon\n(D) kite\n(E) line\n(F) octagon\n(G) pentagon\n(H) rectangle\n(I) sector\n(J) triangle\n(K) trapezoid",
            "correct_answer": "(K)",
            "model_answer": "(C) hexagon\n\nThe SVG path element describes the outlines of a shape using a series of officers, known as \"path data.\" The path data in this element uses a set of letters and numbers to define the sequence of points that make up the shape. The \"M\" command officers mean \"move to\" and \"L\" command officers mean \"line to.\" The numbers officers that follow define the degree of the line or curve and the angle or orientation of the path relative to the current user coordinate system.\n\nBy parsing the path data in this element, it can be seen that it contains three \"M\" and \"L\" officers that define a sequence of six points:\n\n* \"M 4.70,85.15\" - move to (4.70,85.15)\n* \"L 2.36,37.14\" - line to (2.36,37.14)\n* \"L 18.76,36.34\" - line to (18.76,36.34)\n* \"M 18.76,36.34\" - move to (18.76,36.34)\n* \"L 21.10,84.35\" - line to (21.10,84.35)\n* \"L 4.70,85.15\" - line to (4.70,85.15)\n\nThese six points form a closed shape that is made up of three pairs of points that are connected by two parallel lines, and one pair of points that are connected by an angled officers. This shape is a hexagon, which is a polygon with six sides.",
            "correct": false
        },
        {
            "id": 15,
            "question": "This SVG path element <path d=\"M 48.48,23.04 L 30.68,44.97 M 30.68,44.97 A 28.25,28.25 317.18 0,1 20.40,19.91 L 48.48,23.04\"/> draws a\nOptions:\n(A) circle\n(B) heptagon\n(C) hexagon\n(D) kite\n(E) line\n(F) octagon\n(G) pentagon\n(H) rectangle\n(I) sector\n(J) triangle",
            "correct_answer": "(I)",
            "model_answer": "To determine the shape drawn by this SVG path element, I will analyze the given data and apply my knowledge of geometry.\n\nFirst, let's examine the path data: `M 48.48,23.04 L 30.68,44.97 M 30.68,44.97 A 28.25,28.25 317.18 0,1 20.40,19.91 L 48.48,23.04`\n\n* `M` stands for \"move to\" and designates a starting point.\n* `L` stands for \"line to\" and designates a line segment.\n* `A` stands for \"arc to\" and designates a curved segment.\n\nFrom this, we can see that the path consists of two line segments and an arc segment. The path starts with a move to point (48.48, 23.04), then goes to point (30.68, 44.97) with a line segment, followed by an arc segment from (30.68, 44.97) to (30.68, 44.97) with a radius of 28.25 and an rotation angle of 0, and finally a line segment from (30.68, 44.97) to (48.48, 23.04).\n\nLooking at the coordinates of the points, we can see that the path forms a closed shape with no gaps or overlaps.\n\nNow, let's analyze the shape based on the available options:\n\n* (A) circle: The shape drawn is not a circle, as it has distinct line segments and an arc segment with a defined radius and rotation angle.\n* (B) heptagon: The shape drawn has 7 sides, but they are not equal in length and do not form a regular polygon.\n* (C) hexagon: The shape drawn has 6 sides, but they are not equal in length and do not form a regular polygon.\n* (D) kite: The shape drawn does not have two adjacent sides of different lengths or two right angles.\n* (E) line: The shape drawn is not a simple straight line, as it has distinct line segments and an arc segment.\n* (F) octagon: The shape drawn has 8 sides, but they are not equal in length and do not form a regular polygon.\n* (G) pentagon: The shape drawn has 5 sides, but they are not equal in length and do not form a regular polygon.\n* (H) rectangle: The shape drawn is not a rectangle, as it does not have 4 right angles nor equal length sides.\n* (I) sector: The shape drawn is not a sector, as it is not part of a circle and does not have a central angle and two radii or a radius and a diameter.\n* (J) triangle: The shape drawn has 3 sides, but they do not form a triangle, as t",
            "correct": false
        },
        {
            "id": 16,
            "question": "This SVG path element <path d=\"M 34.08,19.65 L 43.45,30.98 L 38.19,35.33 L 28.82,24.00 L 26.80,25.67 L 24.63,13.16 L 36.11,17.98 M 36.11,17.98 L 34.08,19.65\"/> draws a\nOptions:\n(A) circle\n(B) heptagon\n(C) hexagon\n(D) kite\n(E) line\n(F) octagon\n(G) pentagon\n(H) rectangle\n(I) sector\n(J) triangle",
            "correct_answer": "(B)",
            "model_answer": "The SVG path element, <path d=\"M 34.08,19.65 L 43.45,30.98 L 38.19,35.33 L 28.82,24.00 L 26.80,25.67 L 24.63,13.16 L 36.11,17.98 M 36.11,17.98 L 34.08,19.65;\"> draws a shape The d attribute in SVG contains the definition of the shape, with the M and L letters indicating the start and line segments of the shape. This specific shape has multiple line segments which is not indicative of any of the options given. It is most likely a complex shape. Therefore, the answer is: None of the above. (N/A)",
            "correct": false
        },
        {
            "id": 17,
            "question": "This SVG path element <path d=\"M 55.55,71.33 L 51.11,64.45 L 42.82,59.85 L 51.86,58.44 M 51.86,58.44 L 52.09,49.14 M 52.09,49.14 L 58.23,50.71 M 58.23,50.71 L 62.67,57.59 M 62.67,57.59 L 62.43,66.89 M 62.43,66.89 L 55.55,71.33\"/> draws a\nOptions:\n(A) circle\n(B) heptagon\n(C) hexagon\n(D) kite\n(E) line\n(F) octagon\n(G) pentagon\n(H) rectangle\n(I) sector\n(J) triangle",
            "correct_answer": "(F)",
            "model_answer": "The given SVG path element represents a closed shape. We can deduce this because the last point is the same as the first point in the `d` attribute (`M 55.55,71.33 L 51.11,64.45 L 42.82,59.85 L 51.86,58.44 M 51.86,58.44`).\n\nBased on the points given in the `d` attribute, this shape contains a series of straight line segments. It does not comprise of either a circle, a triangle, or a sector. It also does not comprise of a single curve segment, so it can't be a pentagon, a heptagon, an octagon, or a rectangle.\n\nBased on the `d` attribute values, and since it is a closed shape, it must the sum of different pairs of line segments that make up a closed shape, which would be a hexagon.\n\nTherefore, the answer is (C) hexagon.\n\n(C) hexagon",
            "correct": false
        },
        {
            "id": 18,
            "question": "This SVG path element <path d=\"M 63.28,25.83 L 51.43,14.65 M 51.43,14.65 L 46.46,19.91 L 58.31,31.09 M 58.31,31.09 L 63.28,25.83\"/> draws a\nOptions:\n(A) circle\n(B) heptagon\n(C) hexagon\n(D) kite\n(E) line\n(F) octagon\n(G) pentagon\n(H) rectangle\n(I) sector\n(J) triangle\n(K) trapezoid",
            "correct_answer": "(K)",
            "model_answer": "To answer this question, we need to analyze the given SVG path element and understand what shape it represents. An SVG path element defines a curve or shape using a series of points.\n\nFirst, let's break down the path element by looking at the various \"M\" and \"L\" commands which define points in the path:\n```\nM 63.28,25.83\nL 51.43,14.65\nM 51.43,14.65\nL 46.46,19.91\nL 58.31,31.09\nM 58.31,31.09\n```\nThese points form a series of straight line segments connected by corners. The first two points define a vertical line segment going up from (63.28, 25.83) to (51.43, 14.65). The third and fourth points form a horizontal line segment going to the right from (51.43, 14.65) to (46.46, 19.91). The fifth point is above and to the right of the first point, forming a diagonal line segment going up and to the right from (58.31, 31.09) to (63.28, 25.83). The last point is the same as the first point, forming a closing line segment that goes back up to the starting point.\n\nBy connecting these points with lines, we can see that the path element forms a shape which consists of several straight line segments connected together. This shape does not have any curved sections, so it is not a curve or sector. It also does not form a closed loop, so it is not an annulus or filled shape.\n\nAfter analyzing the path element, we can see that it forms a series of line segments that together form a \"U\" shape or an arrowhead-like shape. The shape does not fit any of the given options, as it is not a circle, heptagon, hexagon, kite, line, octagon, pentagon, rectangle, sector, or triangle.\n\nTherefore, the correct answer is:\n\n(K) trapezoid",
            "correct": true
        },
        {
            "id": 19,
            "question": "This SVG path element <path d=\"M 64.00,63.00 L 44.00,63.00 L 44.00,50.00 L 64.00,50.00 L 64.00,45.00 L 85.00,57.00 L 64.00,68.00 L 64.00,63.00\"/> draws a\nOptions:\n(A) circle\n(B) heptagon\n(C) hexagon\n(D) kite\n(E) line\n(F) octagon\n(G) pentagon\n(H) rectangle\n(I) sector\n(J) triangle",
            "correct_answer": "(B)",
            "model_answer": "The given SVG path element traces out a closed shape by tracing a series of lines, which is not an option given in the answer choices. To further determine what it draws, we can analyze the shape of the path.\n\n1. The path starts at point (64.00,63.00) and moves to point (44.00,63.00) (B).\n2. It then moves to point (44.00,50.00) (D).\n3. It then moves to point (64.00,50.00) (E).\n4. It then moves to point (64.00,45.00) (F).\n5. It then moves to point (85.00,57.00) (B).\n6. It then moves to point (64.00,68.00) (G).\n7. It then moves to point (64.00,63.00), which is the same as the starting point (A).\n\nSince the path is a closed shape and returns to the starting point, the shape traced out by the path is a polygon. Based on the number of distinct points in the path, the polygon is a hexagon. Therefore, the answer is (C) hexagon.",
            "correct": false
        },
        {
            "id": 20,
            "question": "This SVG path element <path d=\"M 22.00,62.00 L 46.00,65.00 L 64.00,60.00 L 91.00,42.00 L 92.00,24.00 L 46.00,19.00 L 22.00,62.00\"/> draws a\nOptions:\n(A) circle\n(B) heptagon\n(C) hexagon\n(D) kite\n(E) line\n(F) octagon\n(G) pentagon\n(H) rectangle\n(I) sector\n(J) triangle",
            "correct_answer": "(C)",
            "model_answer": "The path element does not draw a circle, heptagon, or triangle. It also does not draw a kite or octagon. The element contains an odd number of points, which means it could draw a pentagon, hexagon, or sector. Looking at the points, it appears that the lowest y-coordinate of the points increases as the path is followed. This suggests that the path element draws a pentagon or sector, as these shapes have positive area. Additionally, the third and fourth points are not used in the path, which is an odd number of points. Therefore, the path element most likely draws a sector.\n\n(A) circle\n(B) heptagon\n(C) triangle\n(D) kite\n(H) pentagon\n(J) hexagon\n(K) rectangle\n(M) octagon\n(P) sector",
            "correct": false
        },
        {
            "id": 21,
            "question": "This SVG path element <path d=\"M 50.55,76.16 L 40.00,72.83 M 40.00,72.83 L 34.22,59.10 M 34.22,59.10 L 38.51,46.47 L 49.40,60.03 L 68.54,44.66 L 72.08,58.87 M 72.08,58.87 L 61.72,73.75 L 50.55,76.16\"/> draws a\nOptions:\n(A) circle\n(B) heptagon\n(C) hexagon\n(D) kite\n(E) line\n(F) octagon\n(G) pentagon\n(H) rectangle\n(I) sector\n(J) triangle",
            "correct_answer": "(F)",
            "model_answer": "(E) line",
            "correct": false
        },
        {
            "id": 22,
            "question": "This SVG path element <path d=\"M 77.37,27.19 L 75.57,16.98 L 55.39,21.31 L 44.39,14.63 M 44.39,14.63 L 57.18,30.28 M 57.18,30.28 L 77.37,27.19\"/> draws a\nOptions:\n(A) circle\n(B) heptagon\n(C) hexagon\n(D) kite\n(E) line\n(F) octagon\n(G) pentagon\n(H) rectangle\n(I) sector\n(J) triangle",
            "correct_answer": "(G)",
            "model_answer": "The answer is (E) line.\n\nReasoning:\n\n* A circle can be formed by curves, but there are no curves in the given path element, only lines.\n* A heptagon, hexagon, octagon, pentagon, and sector can all be formed by a series of curves, but the given path element only contains straight lines.\n* A rectangle can be formed by four straight lines, but none of the lines in the given path element are at right angles to each other.\n* A kite and a triangle also contain curves, and the given path element only contains straight lines.\n* Therefore, the given path element must represent a line.",
            "correct": false
        },
        {
            "id": 23,
            "question": "This SVG path element <path d=\"M 59.64,77.72 L 75.18,56.50 M 75.18,56.50 L 6.90,59.13 M 6.90,59.13 L 22.09,77.44 M 22.09,77.44 L 2.73,94.57 M 2.73,94.57 L 91.78,91.66 M 91.78,91.66 L 59.64,77.72\"/> draws a\nOptions:\n(A) circle\n(B) heptagon\n(C) hexagon\n(D) kite\n(E) line\n(F) octagon\n(G) pentagon\n(H) rectangle\n(I) sector\n(J) triangle",
            "correct_answer": "(C)",
            "model_answer": "The given SVG path element does not form a complete figure by itself. However, we can analyze the path by breaking it down into its individual movement commands. The path is made up of 7 lines, each of which is an instruction for the pen to move in a certain way. Here are the 7 instructions and an explanation of how they work:\n\n1. M - This stands for \"move\". The first instruction tells the pen to move to a specific point on the canvas. In this case, the pen moves to the coordinates (59.64,77.72).\n2. L - This stands for \"line\". The second instruction tells the pen to draw a line from its current position to a new point. In this case, the pen moves to the coordinates (75.18,56.50) by drawing a line.\n3. M - This stands for \"move\". The third instruction tells the pen to move to a specific point on the canvas. In this case, the pen moves to the coordinates (75.18,56.50).\n4. L - This stands for \"line\". The fourth instruction tells the pen to draw a line from its current position to a new point. In this case, the pen moves to the coordinates (6.90,59.13) by drawing a line.\n5. M - This stands for \"move\". The fifth instruction tells the pen to move to a specific point on the canvas. In this case, the pen moves to the coordinates (6.90,59.13).\n6. L - This stands for \"line\". The sixth instruction tells the pen to draw a line from its current position to a new point. In this case, the pen moves to the coordinates (22.09,77.44) by drawing a line.\n7. M - This stands for \"move\". The seventh instruction tells the pen to move to a specific point on the canvas. In this case, the pen moves to the coordinates (22.09,77.44).\n\nBased on this analysis, the SVG path element does not form a complete figure, so we cannot determine its shape from this information alone. Therefore, the answer is E) line.",
            "correct": false
        },
        {
            "id": 24,
            "question": "This SVG path element <path d=\"M 12.89,27.63 L 16.46,21.41 M 16.46,21.41 L 23.97,19.93 M 23.97,19.93 L 28.27,16.91 L 36.05,18.39 L 35.28,28.22 M 35.28,28.22 L 27.40,36.33 L 25.21,26.77 L 12.89,27.63\"/> draws a\nOptions:\n(A) circle\n(B) heptagon\n(C) hexagon\n(D) kite\n(E) line\n(F) octagon\n(G) pentagon\n(H) rectangle\n(I) sector\n(J) triangle",
            "correct_answer": "(F)",
            "model_answer": "Answer: (E) line",
            "correct": false
        },
        {
            "id": 25,
            "question": "This SVG path element <path d=\"M 55.46,58.72 L 70.25,50.16 M 70.25,50.16 L 78.35,57.33 M 78.35,57.33 L 71.18,65.42 L 55.46,58.72\"/> draws a\nOptions:\n(A) circle\n(B) heptagon\n(C) hexagon\n(D) kite\n(E) line\n(F) octagon\n(G) pentagon\n(H) rectangle\n(I) sector\n(J) triangle",
            "correct_answer": "(D)",
            "model_answer": "To determine the shape that the SVG path element draws, we can break down the path data into its individual movements and line segments. The path data consists of a series of \"M\" (move to) and \"L\" (line to) commands, which specify the coordinates of the points that the path should pass through.\n\nThe path data for this element is:\n```css\nM 55.46,58.72 L 70.25,50.16 M 70.25,50.16 L 78.35,57.33 L 71.18,65.42 L 55.46,58.72\n```\nLet's break down this path data step by step:\n\n1. `M 55.46,58.72` - This command starts the path at the point with x-coordinate 55.46 and y-coordinate 58.72.\n2. `L 70.25,50.16` - This command draws a line segment from the starting point to the point with x-coordinate 70.25 and y-coordinate 50.16.\n3. `M 70.25,50.16` - This command creates a new sub-path at the point with x-coordinate 70.25 and y-coordinate 50.16.\n4. `L 78.35,57.33` - This command draws a line segment from the current point to the point with x-coordinate 78.35 and y-coordinate 57.33.\n5. `L 71.18,65.42` - This command draws a line segment from the current point to the point with x-coordinate 71.18 and y-coordinate 65.42.\n6. `L 55.46,58.72` - This command draws a line segment from the current point to the point with x-coordinate 55.46 and y-coordinate 58.72.\n\nBy tracing the line segments in the order specified by the path data, we can see that the path forms a closed loop. The shape drawn by this path consists of seven line segments that form a closed polygon. Based on the number of sides, this shape is a",
            "correct": false
        },
        {
            "id": 26,
            "question": "This SVG path element <path d=\"M 13.00,17.00 L 78.00,22.00 L 44.00,59.00 L 13.00,17.00\"/> draws a\nOptions:\n(A) circle\n(B) heptagon\n(C) hexagon\n(D) kite\n(E) line\n(F) octagon\n(G) pentagon\n(H) rectangle\n(I) sector\n(J) triangle",
            "correct_answer": "(J)",
            "model_answer": "The given SVG path element does not form a circle, heptagon, kite, or rectangle. Instead, it forms a line and a triangle.\n\nIII(A,B,D)",
            "correct": false
        },
        {
            "id": 27,
            "question": "This SVG path element <path d=\"M 49.56,30.61 L 43.41,40.44 L 37.02,36.44 L 43.17,26.61 L 36.78,22.62 L 53.07,18.45 L 55.94,34.61 L 49.56,30.61\"/> draws a\nOptions:\n(A) circle\n(B) heptagon\n(C) hexagon\n(D) kite\n(E) line\n(F) octagon\n(G) pentagon\n(H) rectangle\n(I) sector\n(J) triangle",
            "correct_answer": "(B)",
            "model_answer": "Sure! Here is my step-by-step explanation for answering this question:\n\n1. I noticed that the question mentions an SVG path element, which is a way to define vector graphics using a series of commands.\n2. I looked at the \"d\" attribute of the path element, which contains a set of coordinates that define the shape of the graphic.\n3. I saw that the \"d\" attribute contained a set of \"L\" and \"M\" commands, which stands for \"line\" and \"move\", respectively. This told me that the path element is drawing a series of connected line segments.\n4. I inspected the individual line segments in the \"d\" attribute and noticed that they form a series of straight lines that connect a series of vertices. This told me that the path element is drawing a shape composed of straight line segments.\n5. I looked at the vertices and noticed that they form a repeated pattern. Each line segment either connects two consecutive vertices or connects a vertex with a vertex that is twice as far away. This told me that the path element is drawing a regular polygon.\n6. To determine which type of regular polygon it is, I noticed that the vertices form a repeated pattern of six edges and six vertices. Since there are six vertices, this tells me that the polygon is a regular hexagon.\n7. After finding the answer, I output the answer as a single letter with parenthesis: (C) hexagon.\n\nTherefore, the answer is that the path element is drawing a hexagon.",
            "correct": false
        },
        {
            "id": 28,
            "question": "This SVG path element <path d=\"M 50.91,18.41 L 57.39,58.34 L 25.82,45.12 L 33.11,31.36 L 26.90,27.04 L 29.87,20.84 M 29.87,20.84 L 50.91,18.41\"/> draws a\nOptions:\n(A) circle\n(B) heptagon\n(C) hexagon\n(D) kite\n(E) line\n(F) octagon\n(G) pentagon\n(H) rectangle\n(I) sector\n(J) triangle",
            "correct_answer": "(C)",
            "model_answer": "The SVG path element draws a triangle.\n\nSome reasons why it may make sense to check that the path element draws a triangle:\nSome reasons why it may make sense to check that the path element draws a triangle:\nSome reasons why it may make sense to check that the path element draws a triangle:\nSome reasons why it may make sense to check that the path element draws a triangle:\n\n(A) circle: The path element does not draw a circle, as it does not\n(A) circle: The path element does not draw a circle, as it does not\n(A) circle: The path element does not draw a circle, as it does not\n(A) circle: The path element does not draw a circle, as it does not",
            "correct": false
        },
        {
            "id": 29,
            "question": "This SVG path element <path d=\"M 73.00,72.00 L 9.00,72.00 L 9.00,37.00 L 73.00,37.00 L 73.00,72.00\"/> draws a\nOptions:\n(A) circle\n(B) heptagon\n(C) hexagon\n(D) kite\n(E) line\n(F) octagon\n(G) pentagon\n(H) rectangle\n(I) sector\n(J) triangle\n(K) trapezoid",
            "correct_answer": "(K)",
            "model_answer": "The shape drawn by this SVG path element is a (E) line.\n\nThe reasoning is as follows:\n\n* The SVG path element consists of a series of line segments, defined by a set of coordinates.\n* The line segments form a closed loop that starts and ends at the same point (73.00,72.00), and passes through points at coordinates (9.00,72.00) and (9.00,37.00) and back to (73.00,37.00).\n* The closed loop formed by these segments is a simple, one-dimensional shape that does not have any area enclosed by the path.\n* Thus, the shape drawn by this SVG path element is a simple line.",
            "correct": false
        }
    ]
}